Workbook

Sheet Data Sheet
A1: COMPANY NAME | B1: HCL TECHNOLOGIES LTD
A2: LATEST VERSION | B2: 2.1 | F2: Do Not Make any changes to this sheet
A3: CURRENT VERSION | F3: This sheet is auto popuated by Screener
A5: META
A6: Number of shares
A7: Face Value | B7: 2
A8: Current Price | B8: 1183.8
A9: Market Capitalization | B9: 321243.67
A15: PROFIT & LOSS
A16: Report Date | B16: 42825 | C16: 43190 | D16: 43555 | E16: 43921 | F16: 44286 | G16: 44651 | H16: 45016 | I16: 45382 | J16: 45747 | K16: 46112
A17: Sales | B17: 47568 | C17: 50569 | D17: 60427 | E17: 70676 | F17: 75379 | G17: 85651 | H17: 101456 | I17: 109913 | J17: 117055 | K17: 130144
A18: Raw Material Cost | B18: 826 | C18: 1251 | D18: 1615 | E18: 1536 | F18: 1698 | G18: 1473 | H18: 2072 | I18: 1754 | J18: 1976 | K18: 2715
A19: Change in Inventory | B19: 11 | C19: -104 | D19: -81 | F19: 3 | G19: 67 | H19: 67 | I19: -43 | J19: -52 | K19: 106
A20: Power and Fuel | B20: 307 | C20: 313 | D20: 336 | E20: 307 | F20: 275 | G20: 291 | H20: 328 | I20: 360 | J20: 355
A21: Other Mfr. Exp | B21: 9286 | C21: 9388 | D21: 10862 | E21: 12324 | F21: 12084 | G21: 14574 | H21: 17303 | I21: 16651 | J21: 16276
A22: Employee Cost | B22: 22866 | C22: 24729 | D22: 29283 | E22: 34928 | F22: 38853 | G22: 46130 | H22: 55280 | I22: 62480 | J22: 66755 | K22: 74143
A23: Selling and admin | B23: 2988 | C23: 2810 | D23: 3519 | E23: 3050 | F23: 1681 | G23: 1866 | H23: 2687 | I23: 2858 | J23: 4504
A24: Other Expenses | B24: 916 | C24: 728 | D24: 805 | E24: 1215 | F24: 743 | G24: 855 | H24: 1225 | I24: 1569 | J24: 1633 | K24: 26640
A25: Other Income | B25: 1069 | C25: 1230 | D25: 943 | E25: 589 | F25: 927 | G25: 1067 | H25: 1358 | I25: 1495 | J25: 2485 | K25: 574
A26: Depreciation | B26: 828 | C26: 1383 | D26: 2073 | E26: 3420 | F26: 4611 | G26: 4326 | H26: 4145 | I26: 4173 | J26: 4084 | K26: 4355
A27: Interest | B27: 89 | C27: 69 | D27: 174 | E27: 505 | F27: 511 | G27: 319 | H27: 353 | I27: 553 | J27: 644 | K27: 869
A28: Profit before tax | B28: 10542 | C28: 11024 | D28: 12622 | E28: 13980 | F28: 15853 | G28: 16951 | H28: 19488 | I28: 20967 | J28: 23261 | K28: 22102
A29: Tax | B29: 1936 | C29: 2302 | D29: 2502 | E29: 2923 | F29: 4684 | G29: 3428 | H29: 4643 | I29: 5257 | J29: 5862 | K29: 5450
A30: Net profit | B30: 8606 | C30: 8721 | D30: 10120 | E30: 11057 | F30: 11145 | G30: 13499 | H30: 14851 | I30: 15702 | J30: 17390 | K30: 16642
A31: Dividend Amount | B31: 3420 | C31: 1668 | D31: 1084 | E31: 2715 | F31: 2715 | G31: 11403 | H31: 13032 | I31: 14118 | J31: 16290 | K31: 14661
A40: Quarters
A41: Report Date | B41: 45291 | C41: 45382 | D41: 45473 | E41: 45565 | F41: 45657 | G41: 45747 | H41: 45838 | I41: 45930 | J41: 46022 | K41: 46112
A42: Sales | B42: 28446 | C42: 28499 | D42: 28057 | E42: 28862 | F42: 29890 | G42: 30246 | H42: 30349 | I42: 31942 | J42: 33872 | K42: 33981
A43: Expenses | B43: 21659 | C43: 22382 | D43: 22264 | E43: 22493 | F43: 23030 | G43: 23764 | H43: 24314 | I43: 25397 | J43: 26460 | K43: 27269
A44: Other Income | B44: 370 | C44: 416 | D44: 1103 | E44: 456 | F44: 477 | G44: 449 | H44: 456 | I44: 415 | J44: -571 | K44: 322
A45: Depreciation | B45: 1143 | C45: 1093 | D45: 998 | E45: 1007 | F45: 1039 | G45: 1040 | H45: 1093 | I45: 1043 | J45: 1127 | K45: 1092
A46: Interest | B46: 140 | C46: 171 | D46: 191 | E46: 131 | F46: 166 | G46: 156 | H46: 209 | I46: 215 | J46: 205 | K46: 240
A47: Profit before tax | B47: 5874 | C47: 5269 | D47: 5707 | E47: 5687 | F47: 6132 | G47: 5735 | H47: 5189 | I47: 5702 | J47: 5509 | K47: 5702
A48: Tax | B48: 1523 | C48: 1274 | D48: 1448 | E48: 1450 | F48: 1538 | G48: 1426 | H48: 1345 | I48: 1466 | J48: 1427 | K48: 1212
A49: Net profit | B49: 4350 | C49: 3986 | D49: 4257 | E49: 4235 | F49: 4591 | G49: 4307 | H49: 3843 | I49: 4235 | J49: 4076 | K49: 4488
A50: Operating Profit | B50: 6787 | C50: 6117 | D50: 5793 | E50: 6369 | F50: 6860 | G50: 6482 | H50: 6035 | I50: 6545 | J50: 7412 | K50: 6712
A55: BALANCE SHEET
A56: Report Date | B56: 42825 | C56: 43190 | D56: 43555 | E56: 43921 | F56: 44286 | G56: 44651 | H56: 45016 | I56: 45382 | J56: 45747 | K56: 46112
A57: Equity Share Capital | B57: 285 | C57: 278 | D57: 271 | E57: 543 | F57: 543 | G57: 543 | H57: 543 | I57: 543 | J57: 543 | K57: 543
A58: Reserves | B58: 32664 | C58: 36108 | D58: 41095 | E58: 50724 | F58: 59370 | G58: 61371 | H58: 64862 | I58: 67720 | J58: 69112 | K58: 74622
A59: Borrowings | B59: 582 | C59: 557 | D59: 4195 | E59: 7986 | F59: 6864 | G59: 6343 | H59: 4794 | I59: 5758 | J59: 6276 | K59: 5215
A60: Other Liabilities | B60: 12231 | C60: 11046 | D60: 12788 | E60: 23566 | F60: 19270 | G60: 20664 | H60: 23051 | I60: 24985 | J60: 28549 | K60: 35878
A61: Total | B61: 45762 | C61: 47989 | D61: 58349 | E61: 82819 | F61: 86047 | G61: 88921 | H61: 93250 | I61: 99006 | J61: 104480 | K61: 116258
A62: Net Block | B62: 15235 | C62: 18753 | D62: 22888 | E62: 37490 | F62: 37145 | G62: 35077 | H62: 34619 | I62: 35063 | J62: 36172 | K62: 37379
A63: Capital Work in Progress | B63: 448 | C63: 320 | D63: 235 | E63: 400 | F63: 312 | G63: 129 | H63: 40 | I63: 108 | J63: 59 | K63: 60
A64: Investments | B64: 1306 | C64: 2660 | D64: 2305 | E64: 7066 | F64: 6862 | G64: 6351 | H64: 5495 | I64: 7137 | J64: 7564 | K64: 7090
A65: Other Assets | B65: 28773 | C65: 26256 | D65: 32921 | E65: 37863 | F65: 41728 | G65: 47364 | H65: 53096 | I65: 56698 | J65: 60685 | K65: 71729
A66: Total | B66: 45762 | C66: 47989 | D66: 58349 | E66: 82819 | F66: 86047 | G66: 88921 | H66: 93250 | I66: 99006 | J66: 104480 | K66: 116258
A67: Receivables | B67: 8301 | C67: 9639 | D67: 11706 | E67: 14131 | F67: 17525 | G67: 20671 | H67: 25506 | I67: 25521 | J67: 25842 | K67: 23585
... A69: Cash & Bank | B69: 9044 | C69: 4018 | D69: 7872 | E69: 4976 | F69: 8888 | G69: 12636 | H69: 14724 | I69: 20150 | J69: 21289 | K69: 23425
A70: No. of Equity Shares | B70: 1426783424 | C70: 1392246384 | D70: 1356278868 | E70: 2713665096 | F70: 2713665096 | G70: 2713665096 | H70: 2713665096 | I70: 2713665096 | J70: 2713665096
A71: New Bonus Shares
A72: Face value | B72: 2 | C72: 2 | D72: 2 | E72: 2 | F72: 2 | G72: 2 | H72: 2 | I72: 2 | J72: 2 | K72: 2
A80: CASH FLOW:
A81: Report Date | B81: 42825 | C81: 43190 | D81: 43555 | E81: 43921 | F81: 44286 | G81: 44651 | H81: 45016 | I81: 45382 | J81: 45747 | K81: 46112
A82: Cash from Operating Activity | B82: 8995 | C82: 8328 | D82: 8971 | E82: 13359 | F82: 19618 | G82: 16900 | H82: 18009 | I82: 22448 | J82: 22261 | K82: 19975
A83: Cash from Investing Activity | B83: -3890 | C83: -2236 | D83: -3256 | E83: -12332 | F83: -5665 | G83: 1597 | H83: -3573 | I83: -6608 | J83: -4896 | K83: -1473
A84: Cash from Financing Activity | B84: -4517 | C84: -5714 | D84: -1471 | E84: -3168 | F84: -11192 | G84: -14508 | H84: -15881 | I84: -15464 | J84: -18561 | K84: -19369
A85: Net Cash Flow | B85: 588 | C85: 378 | D85: 4244 | E85: -2141 | F85: 2761 | G85: 3989 | H85: -1445 | I85: 376 | J85: -1196 | K85: -867
A90: PRICE: | B90: 437.38 | C90: 484.3 | D90: 543.73 | E90: 436.4 | F90: 982.65 | G90: 1163.75 | H90: 1085.25 | I90: 1543.55 | J90: 1592.5 | K90: 1341.6
A92: DERIVED:
A93: Adjusted Equity Shares in Cr | B93: 285.36 | C93: 278.45 | D93: 271.26 | E93: 271.37 | F93: 271.37 | G93: 271.37 | H93: 271.37 | I93: 271.37 | J93: 271.37 | K93: 271.37
A99: Stock Price

Sheet 📋 Cover
B1: DCF VALUATION MODEL v3.0 — IT / TECHNOLOGY SERVICES
B2: Indian Listed IT Companies · Screener.in + Trendlyne + CompaniesMarketCap · IT-Specific Assumptions Engine
B3: 🖥️ SECTOR: IT / TECHNOLOGY SERVICES
B4: COMPANY DETAILS
B5: Company Name
B6: Ticker
B7: Sector
B8: Valuation Date
B9: Analyst
B11: COLOR LEGEND — CRITICAL TO UNDERSTAND
B12: Blue / Light blue → Historical INPUT (paste from Screener.in)
B13: Blue / Yellow → KEY INPUT (FY2027-28 from Market Screener, or your judgment)
... B19: PROJECTION METHODOLOGY — IT SERVICES SPECIFIC
B20: Revenue Growth % | D20: FY2027-28: Trendlyne Forecaster analyst consensus → FY2029-34: Linear taper from FY2028 to terminal g (5–6%) by FY2034
B21: EBITDA Margin % | D21: FY2027-28: Trendlyne analyst consensus → FY2029-34: Excel TREND function on 7 data points. IT margins are structurally stable (20–25% band).
B22: D&A / Revenue % | D22: FY2027-28: Derived as (EBITDA% − EBIT%) from Trendlyne → FY2029-34: TREND function (NOT median — IT D&A is trending up due to Ind AS 116 lease accounting)
B23: Capex % Revenue | D23: IT-SPECIFIC: Modelled as % of revenue (1.5–3%), NOT absolute ₹ taper. Capex scales with headcount. FY2027-28: Trendlyne. FY2029-34: held flat at FY2028 level.
B24: Working Capital | D24: NWC % OF REVENUE approach. Historical NWC% auto-calculated from Hist Data. FY2027-28: user inputs NWC% (default = 5Y hist avg). FY2029+: flat at FY2028 level. ΔWC = (NWC% × Revenue_N) − (NWC% × Revenue_N-1). No separate debtor/creditor day assumptions needed.
B25: Other Income | D25: IT-SPECIFIC: Modelled as Net Cash Balance × Treasury Yield %. IT majors earn ₹3,000–6,000 Cr/yr in interest income on cash pile. NOT flat carry-forward.
B26: Debt Schedule | D26: FY2027-28: Trendlyne Net Debt forecast. FY2029-34: linear to zero (IT companies are net cash). Equity bridge handles NEGATIVE net debt (net cash) correctly.
B27: QUICK START — 6 STEPS
B28: QUICK START — 7 STEPS (IT Services) | C28: 📊 Hist Data | D28: Paste 5Y P&L + BS + CF from Screener.in into blue cells. Enter Market Cap & Shares in yellow.
B29: Step 1 | C29: 📊 Hist Data | D29: Paste 5Y P&L + BS + CF from Screener.in. Market Cap/Shares from CompaniesMarketCap.com.
B30: Step 2 | C30: 📊 Hist Data S5 | D30: NEW: Paste Unbilled Revenue + Deferred Revenue (5Y) from Screener BS expanded view.
B31: Step 3 | C31: 🔑 Assumptions A | D31: Company name, ticker, IT sub-sector, tax rate (use Screener effective rate ~20-23%), terminal g.
B32: Step 4 | C32: 🔑 Assumptions B | D32: Yellow cells: Revenue growth + EBITDA margin + D&A% from Trendlyne Forecaster. Purple = auto.
B33: Step 5 | C33: 🔑 Assumptions C | D33: Capex % of Revenue (from Trendlyne). WC days including Unbilled + Deferred Revenue days.
B34: Step 6 | C34: 🔑 Assumptions F | D34: Rf (RBI 10Y G-Sec), ERP (Damodaran India), Beta (Trendlyne). WACC auto-calculated.
B35: Step 7 | C35: 💰 FCF & Val | D35: Intrinsic value per share auto-populated. Net cash bridge handled automatically.
B37: DATA SOURCES — WHERE TO GET EVERY NUMBER
B38: What You Need | C38: Source | D38: Exact Location / Instructions
B39: Historical P&L (Sales, EBITDA, D&A, Interest, PAT) | C39: Screener.in | D39: Company page → P&L tab → Copy 5 years
B40: Historical Balance Sheet (Debt, Cash, Receivables, etc.) | C40: Screener.in | D40: Company page → Balance Sheet tab → Expand rows
B41: Historical Cash Flow (CFO, Capex, FCF) | C41: Screener.in | D41: Company page → Cash Flows tab
B42: Unbilled Revenue + Deferred Revenue (historical) | C42: Screener.in | D42: Balance Sheet → expand "Other Assets" / "Other Liabilities"
B43: Beta (3-year) | C43: Screener.in / Trendlyne | D43: Screener company page (shown directly) OR Trendlyne → Technicals
B44: Market Cap + Shares Outstanding (historical) | C44: CompaniesMarketCap.com | D44: Search company → Market Cap History → Annual data
B45: Revenue + EBITDA + Capex forecasts FY2027-28 | C45: Trendlyne Forecaster | D45: Company page → Forecaster tab → Estimates (Premium)
B46: Revenue + EBITDA forecasts FY2027-28 (alternative) | C46: Market Screener | D46: Company → Financials → Estimates (Premium)
B47: Risk-Free Rate (10Y G-Sec yield) | C47: RBI / Investing.com | D47: investing.com → search "India 10 Year Bond Yield" → current yield
B48: Equity Risk Premium (India ERP) | C48: Damodaran (NYU) | D48: pages.stern.nyu.edu/~adamodar → Implied ERP → India
B49: Effective Tax Rate | C49: Screener.in | D49: P&L tab → Tax % row → use AVERAGE of last 3 years (IT: ~20-23%)
B50: Current Market Price (CMP) | C50: NSE / BSE / Google | D50: Search "[TICKER] share price" → current price

Sheet 📊 Hist Data
B1: HISTORICAL FINANCIALS — IT SERVICES | ₹ Crores | Upload to screener.in/excel/ → Export to Excel for any company → Dark green cells fill automatically
B2: 🟢 DARK GREEN = auto from Data Sheet (Screener export) | 🔵 LIGHT BLUE = manual entry (Screener BS/CF expand view) | 🟡 YELLOW = manual input (Market Cap, WACC inputs, Trendlyne forecasts)
B3: SECTION 1 — PROFIT & LOSS | 🟢 Dark Green = auto from Screener Data Sheet | 🔵 Light Blue = manual from Screener expanded view
B4: Screener Label | C4: =IFERROR("FY"&TEXT('Data Sheet'!G16,"YYYY"),"FY2022") -> FY2022 | D4: =IFERROR("FY"&TEXT('Data Sheet'!H16,"YYYY"),"FY2023") -> FY2023 | E4: =IFERROR("FY"&TEXT('Data Sheet'!I16,"YYYY"),"FY2024") -> FY2024 | F4: =IFERROR("FY"&TEXT('Data Sheet'!J16,"YYYY"),"FY2025") -> FY2025 | G4: =IFERROR("FY"&TEXT('Data Sheet'!K16,"YYYY"),"FY2026") -> FY2026 | I4: SOURCE → WHERE TO GET THIS DATA
B5: Sales | C5: =IFERROR('Data Sheet'!G17,0) -> 85651 | D5: =IFERROR('Data Sheet'!H17,0) -> 101456 | E5: =IFERROR('Data Sheet'!I17,0) -> 109913 | F5: =IFERROR('Data Sheet'!J17,0) -> 117055 | G5: =IFERROR('Data Sheet'!K17,0) -> 130144 | I5: 🟢 AUTO from Data Sheet row 17 (Sales). Screener fills this when you Export to Excel.
B6: Operating Profit (EBITDA) | C6: =IFERROR('Data Sheet'!G28+'Data Sheet'!G26+'Data Sheet'!G27-'Data Sheet'!G25,0) -> 20529 | D6: =IFERROR('Data Sheet'!H28+'Data Sheet'!H26+'Data Sheet'!H27-'Data Sheet'!H25,0) -> 22628 | E6: =IFERROR('Data Sheet'!I28+'Data Sheet'!I26+'Data Sheet'!I27-'Data Sheet'!I25,0) -> 24198 | F6: =IFERROR('Data Sheet'!J28+'Data Sheet'!J26+'Data Sheet'!J27-'Data Sheet'!J25,0) -> 25504 | G6: =IFERROR('Data Sheet'!K28+'Data Sheet'!K26+'Data Sheet'!K27-'Data Sheet'!K25,0) -> 26752 | I6: 🟢 AUTO: EBITDA = PBT + D&A + Interest − Other Income (all from Data Sheet). Cross-check: should match Screener Operating Profit.
B7: Other Income | C7: =IFERROR('Data Sheet'!G25,0) -> 1067 | D7: =IFERROR('Data Sheet'!H25,0) -> 1358 | E7: =IFERROR('Data Sheet'!I25,0) -> 1495 | F7: =IFERROR('Data Sheet'!J25,0) -> 2485 | G7: =IFERROR('Data Sheet'!K25,0) -> 574 | I7: 🟢 AUTO from Data Sheet row 25 (Other Income).
B8: Interest | C8: =IFERROR('Data Sheet'!G27,0) -> 319 | D8: =IFERROR('Data Sheet'!H27,0) -> 353 | E8: =IFERROR('Data Sheet'!I27,0) -> 553 | F8: =IFERROR('Data Sheet'!J27,0) -> 644 | G8: =IFERROR('Data Sheet'!K27,0) -> 869 | I8: 🟢 AUTO from Data Sheet row 27 (Interest).
B9: Depreciation (D&A) | C9: =IFERROR('Data Sheet'!G26,0) -> 4326 | D9: =IFERROR('Data Sheet'!H26,0) -> 4145 | E9: =IFERROR('Data Sheet'!I26,0) -> 4173 | F9: =IFERROR('Data Sheet'!J26,0) -> 4084 | G9: =IFERROR('Data Sheet'!K26,0) -> 4355 | I9: 🟢 AUTO from Data Sheet row 26 (Depreciation).
B10: Profit Before Tax | C10: =IFERROR('Data Sheet'!G28,0) -> 16951 | D10: =IFERROR('Data Sheet'!H28,0) -> 19488 | E10: =IFERROR('Data Sheet'!I28,0) -> 20967 | F10: =IFERROR('Data Sheet'!J28,0) -> 23261 | G10: =IFERROR('Data Sheet'!K28,0) -> 22102 | I10: 🟢 AUTO from Data Sheet row 28 (Profit Before Tax).
B11: Tax % (effective) | C11: =IFERROR('Data Sheet'!G29/'Data Sheet'!G28,0) -> 0.20222996 | D11: =IFERROR('Data Sheet'!H29/'Data Sheet'!H28,0) -> 0.23824918 | E11: =IFERROR('Data Sheet'!I29/'Data Sheet'!I28,0) -> 0.25072733 | F11: =IFERROR('Data Sheet'!J29/'Data Sheet'!J28,0) -> 0.2520098 | G11: =IFERROR('Data Sheet'!K29/'Data Sheet'!K28,0) -> 0.24658402 | I11: 🟢 AUTO: Tax % = Data Sheet Tax Amount ÷ PBT. This is effective tax rate (what company actually paid). IT companies: typically 20-23% due to SEZ/STPI benefits.
B12: Tax Amount (₹ Cr) | C12: =IFERROR('Data Sheet'!G29,0) -> 3428 | D12: =IFERROR('Data Sheet'!H29,0) -> 4643 | E12: =IFERROR('Data Sheet'!I29,0) -> 5257 | F12: =IFERROR('Data Sheet'!J29,0) -> 5862 | G12: =IFERROR('Data Sheet'!K29,0) -> 5450
B13: Effective Tax Rate % | C13: =IFERROR(C12/C10,0) -> 0.20222996 | D13: =IFERROR(D12/D10,0) -> 0.23824918 | E13: =IFERROR(E12/E10,0) -> 0.25072733 | F13: =IFERROR(F12/F10,0) -> 0.2520098 | G13: =IFERROR(G12/G10,0) -> 0.24658402
B14: Net Profit | C14: =IFERROR('Data Sheet'!G30,0) -> 13499 | D14: =IFERROR('Data Sheet'!H30,0) -> 14851 | E14: =IFERROR('Data Sheet'!I30,0) -> 15702 | F14: =IFERROR('Data Sheet'!J30,0) -> 17390 | G14: =IFERROR('Data Sheet'!K30,0) -> 16642 | I14: 🟢 AUTO from Data Sheet row 30 (Net Profit). Note: this is consolidated PAT. Small diff from PAT to equity due to minority interest.
B15: Minority Share | C15: -24 | D15: 6 | E15: -8 | F15: -9 | G15: -10 | I15: 🔵 MANUAL: Screener BS → expand Other Liabilities → Non-controlling interest. Enter as NEGATIVE if minority is profitable (reduces equity PAT).
B16: PAT to Equity | C16: =IFERROR(C14+C15,0) -> 13475 | D16: =IFERROR(D14+D15,0) -> 14857 | E16: =IFERROR(E14+E15,0) -> 15694 | F16: =IFERROR(F14+F15,0) -> 17381 | G16: =IFERROR(G14+G15,0) -> 16632
B17: Screener Label
B18: EBIT (₹ Cr) | C18: =IFERROR(C6-C9,0) -> 16203 | D18: =IFERROR(D6-D9,0) -> 18483 | E18: =IFERROR(E6-E9,0) -> 20025 | F18: =IFERROR(F6-F9,0) -> 21420 | G18: =IFERROR(G6-G9,0) -> 22397
B19: EBITDA Margin % | C19: =IFERROR(C6/C5,0) -> 0.23968197 | D19: =IFERROR(D6/D5,0) -> 0.22303264 | E19: =IFERROR(E6/E5,0) -> 0.22015594 | F19: =IFERROR(F6/F5,0) -> 0.21788048 | G19: =IFERROR(G6/G5,0) -> 0.20555692 | I19: → Used in Assumptions B. IT range: 20-27%. TCS ~26%, Infosys ~23%, HCL ~20%.
B20: PAT to Equity Margin % | C20: =IFERROR(C16/C5,0) -> 0.15732449 | D20: =IFERROR(D16/D5,0) -> 0.14643786 | E20: =IFERROR(E16/E5,0) -> 0.14278566 | F20: =IFERROR(F16/F5,0) -> 0.14848575 | G20: =IFERROR(G16/G5,0) -> 0.1277969
B21: Revenue Growth % YoY | C21: "-" | D21: =IFERROR((D5-C5)/C5,0) -> 0.18452791 | E21: =IFERROR((E5-D5)/D5,0) -> 0.083356332 | F21: =IFERROR((F5-E5)/E5,0) -> 0.064978665 | G21: =IFERROR((G5-F5)/F5,0) -> 0.11181923 | I21: → Used in Assumptions B. IT avg growth: 8-15% for large caps.
B23: SECTION 2 — BALANCE SHEET | 🟢 Total BS items auto | 🔵 Borrowings breakdown + Trade Payables = manual (Screener expand)
B24: LIABILITIES
B25: Screener Label | C25: =IFERROR("FY"&TEXT('Data Sheet'!G16,"YYYY"),"FY2022") -> FY2022 | D25: =IFERROR("FY"&TEXT('Data Sheet'!H16,"YYYY"),"FY2023") -> FY2023 | E25: =IFERROR("FY"&TEXT('Data Sheet'!I16,"YYYY"),"FY2024") -> FY2024 | F25: =IFERROR("FY"&TEXT('Data Sheet'!J16,"YYYY"),"FY2025") -> FY2025 | G25: =IFERROR("FY"&TEXT('Data Sheet'!K16,"YYYY"),"FY2026") -> FY2026
B26: Equity Capital | C26: =IFERROR('Data Sheet'!G57,0) -> 543 | D26: =IFERROR('Data Sheet'!H57,0) -> 543 | E26: =IFERROR('Data Sheet'!I57,0) -> 543 | F26: =IFERROR('Data Sheet'!J57,0) -> 543 | G26: =IFERROR('Data Sheet'!K57,0) -> 543 | I26: 🟢 AUTO from Data Sheet row 57 (Equity Share Capital).
B27: Reserves | C27: =IFERROR('Data Sheet'!G58,0) -> 61371 | D27: =IFERROR('Data Sheet'!H58,0) -> 64862 | E27: =IFERROR('Data Sheet'!I58,0) -> 67720 | F27: =IFERROR('Data Sheet'!J58,0) -> 69112 | G27: =IFERROR('Data Sheet'!K58,0) -> 74622 | I27: 🟢 AUTO from Data Sheet row 58 (Reserves).
B28: Total Equity | C28: =IFERROR(C26+C27,0) -> 61914 | D28: =IFERROR(D26+D27,0) -> 65405 | E28: =IFERROR(E26+E27,0) -> 68263 | F28: =IFERROR(F26+F27,0) -> 69655 | G28: =IFERROR(G26+G27,0) -> 75165
B29: Borrowings (Total) | C29: =IFERROR('Data Sheet'!G59,0) -> 6343 | D29: =IFERROR('Data Sheet'!H59,0) -> 4794 | E29: =IFERROR('Data Sheet'!I59,0) -> 5758 | F29: =IFERROR('Data Sheet'!J59,0) -> 6276 | G29: =IFERROR('Data Sheet'!K59,0) -> 5215 | I29: 🟢 AUTO from Data Sheet row 59 (Total Borrowings). For LT/ST/Lease breakdown below: manually enter from Screener BS expanded view.
B30: Long-Term Borrowings | C30: 3923 | D30: 2111 | E30: 2223 | F30: 70 | G30: 37 | I30: 🔵 MANUAL: Screener BS → expand Borrowings → Long Term Borrowings
B31: Short-Term Borrowings | C31: 62 | D31: 140 | E31: 104 | F31: 2221 | G31: 122 | I31: 🔵 MANUAL: Screener BS → expand Borrowings → Short Term Borrowings
B32: Lease Liabilities | C32: 2358 | D32: 2535 | E32: 3429 | F32: 3985 | G32: 5056 | I32: 🔵 MANUAL: Screener BS → expand Borrowings → Lease Liabilities (Ind AS 116)
B33: Non-Controlling Interest | C33: 92 | D33: -7 | E33: 8 | F33: 18 | G33: 32 | I33: 🔵 MANUAL: Screener BS → expand Other Liab → Non-controlling int. Not in Data Sheet.
B34: Trade Payables | C34: 6278 | D34: 6428 | E34: 5853 | F34: 6225 | G34: 7706 | I34: 🔵 MANUAL: Screener BS → expand Other Liab → Trade Payables. Not in Data Sheet.
B35: Advance From Customers | C35: 222 | D35: 252 | E35: 158 | F35: 204 | I35: 🔵 MANUAL: Screener BS → expand Other Liab → Advance from Customers / Deferred Revenue.
B36: Other Liability Items | C36: 14072 | D36: 16378 | E36: 18966 | F36: 22102 | G36: 28140 | I36: 🔵 MANUAL: Screener BS → expand Other Liab → Other liability items. Not in Data Sheet.
B37: TOTAL LIABILITIES | C37: =SUM(C28:C29,C33:C36) -> 88921 | D37: =SUM(D28:D29,D33:D36) -> 93250 | E37: =SUM(E28:E29,E33:E36) -> 99006 | F37: =SUM(F28:F29,F33:F36) -> 104480 | G37: =SUM(G28:G29,G33:G36) -> 116258 | I37: BS → 'Total Liabilities' — cross-check
B38: ASSETS
B39: Screener Label
B40: Fixed Assets (Net Block) | C40: =IFERROR('Data Sheet'!G62,0) -> 35077 | D40: =IFERROR('Data Sheet'!H62,0) -> 34619 | E40: =IFERROR('Data Sheet'!I62,0) -> 35063 | F40: =IFERROR('Data Sheet'!J62,0) -> 36172 | G40: =IFERROR('Data Sheet'!K62,0) -> 37379 | I40: 🟢 AUTO from Data Sheet row 62 (Net Block).
B41: Capital WIP | C41: =IFERROR('Data Sheet'!G63,0) -> 129 | D41: =IFERROR('Data Sheet'!H63,0) -> 40 | E41: =IFERROR('Data Sheet'!I63,0) -> 108 | F41: =IFERROR('Data Sheet'!J63,0) -> 59 | G41: =IFERROR('Data Sheet'!K63,0) -> 60 | I41: 🟢 AUTO from Data Sheet row 63 (Capital Work in Progress).
B42: Investments | C42: =IFERROR('Data Sheet'!G64,0) -> 6351 | D42: =IFERROR('Data Sheet'!H64,0) -> 5495 | E42: =IFERROR('Data Sheet'!I64,0) -> 7137 | F42: =IFERROR('Data Sheet'!J64,0) -> 7564 | G42: =IFERROR('Data Sheet'!K64,0) -> 7090 | I42: 🟢 AUTO from Data Sheet row 64 (Investments).
B43: Inventories | C43: =IFERROR('Data Sheet'!G68,0) -> 161 | D43: =IFERROR('Data Sheet'!H68,0) -> 228 | E43: =IFERROR('Data Sheet'!I68,0) -> 185 | F43: =IFERROR('Data Sheet'!J68,0) -> 133 | G43: =IFERROR('Data Sheet'!K68,0) -> 239 | I43: 🟢 AUTO from Data Sheet row 68 (Inventory). IT companies: should be ~0.
B44: Trade Receivables | C44: =IFERROR('Data Sheet'!G67,0) -> 20671 | D44: =IFERROR('Data Sheet'!H67,0) -> 25506 | E44: =IFERROR('Data Sheet'!I67,0) -> 25521 | F44: =IFERROR('Data Sheet'!J67,0) -> 25842 | G44: =IFERROR('Data Sheet'!K67,0) -> 23585 | I44: 🟢 AUTO from Data Sheet row 67 (Receivables). IT benchmark: 60-90 debtor days.
B45: Cash & Equivalents | C45: =IFERROR('Data Sheet'!G69,0) -> 12636 | D45: =IFERROR('Data Sheet'!H69,0) -> 14724 | E45: =IFERROR('Data Sheet'!I69,0) -> 20150 | F45: =IFERROR('Data Sheet'!J69,0) -> 21289 | G45: =IFERROR('Data Sheet'!K69,0) -> 23425 | I45: 🟢 AUTO from Data Sheet row 69 (Cash & Bank). ⚠ Note: Screener Cash may include some treasury investments. For precise split, check Annual Report.
B46: Loans & Advances | C46: 1819 | D46: 1967 | E46: 2114 | F46: 2753 | G46: 5253 | I46: 🔵 MANUAL: Screener BS → expand Other Assets → Loans n Advances. Not separately available in Data Sheet.
B47: Other Asset Items | C47: 12077 | D47: 10671 | E47: 8728 | F47: 10668 | G47: 19227 | I47: 🔵 MANUAL: Screener BS → expand Other Assets → Other asset items. Not separately available in Data Sheet.
B48: TOTAL ASSETS | C48: =IFERROR(C40+C41+C42+C43+C44+C45+C46+C47,0) -> 88921 | D48: =IFERROR(D40+D41+D42+D43+D44+D45+D46+D47,0) -> 93250 | E48: =IFERROR(E40+E41+E42+E43+E44+E45+E46+E47,0) -> 99006 | F48: =IFERROR(F40+F41+F42+F43+F44+F45+F46+F47,0) -> 104480 | G48: =IFERROR(G40+G41+G42+G43+G44+G45+G46+G47,0) -> 116258
B50: BALANCE SHEET CHECK (must = 0) | C50: =C48-C37 -> 0 | D50: =D48-D37 -> 0 | E50: =E48-E37 -> 0 | F50: =F48-F37 -> 0 | G50: =G48-G37 -> 0 | I50: Must be 0 (±5 Cr rounding ok)
B52: SECTION 3 — CASH FLOW | 🟢 CFO + CFI auto | 🔵 Capex + WC Changes = manual (Screener CF expand)
B53: Screener Label | C53: =IFERROR("FY"&TEXT('Data Sheet'!G16,"YYYY"),"FY2022") -> FY2022 | D53: =IFERROR("FY"&TEXT('Data Sheet'!H16,"YYYY"),"FY2023") -> FY2023 | E53: =IFERROR("FY"&TEXT('Data Sheet'!I16,"YYYY"),"FY2024") -> FY2024 | F53: =IFERROR("FY"&TEXT('Data Sheet'!J16,"YYYY"),"FY2025") -> FY2025 | G53: =IFERROR("FY"&TEXT('Data Sheet'!K16,"YYYY"),"FY2026") -> FY2026
B54: Cash from Operating Activity | C54: =IFERROR('Data Sheet'!G82,0) -> 16900 | D54: =IFERROR('Data Sheet'!H82,0) -> 18009 | E54: =IFERROR('Data Sheet'!I82,0) -> 22448 | F54: =IFERROR('Data Sheet'!J82,0) -> 22261 | G54: =IFERROR('Data Sheet'!K82,0) -> 19975 | I54: 🟢 AUTO from Data Sheet row 82 (Cash from Operating Activity).
B55: Working Capital Changes | C55: -549 | D55: -1305 | E55: 2305 | F55: 1010 | G55: -1522 | I55: 🔵 MANUAL: Screener CF → expand Operating → Working capital changes. Not separately in Data Sheet.
B56: Cash from Investing Activity | C56: =IFERROR('Data Sheet'!G83,0) -> 1597 | D56: =IFERROR('Data Sheet'!H83,0) -> -3573 | E56: =IFERROR('Data Sheet'!I83,0) -> -6608 | F56: =IFERROR('Data Sheet'!J83,0) -> -4896 | G56: =IFERROR('Data Sheet'!K83,0) -> -1473 | I56: 🟢 AUTO from Data Sheet row 83 (Cash from Investing Activity).
B57: Capex (Fixed Assets Purch.) | C57: -1645 | D57: -1661 | E57: -1048 | F57: -1108 | G57: -1422 | I57: 🔵 MANUAL: Screener CF → expand Investing → Fixed assets purchased (enter as negative). Not separately in Data Sheet.
B58: Free Cash Flow (Screener) | C58: 15345 | D58: 16565 | E58: 21432 | F58: 21178 | G58: 18576 | I58: CF → 'Free Cash Flow' — cross-check vs model
B60: SECTION 4 — KEY METRICS (feeds Assumptions WACC — do not skip)
B61: Screener Label | C61: =IFERROR("FY"&TEXT('Data Sheet'!G16,"YYYY"),"FY2022") -> FY2022 | D61: =IFERROR("FY"&TEXT('Data Sheet'!H16,"YYYY"),"FY2023") -> FY2023 | E61: =IFERROR("FY"&TEXT('Data Sheet'!I16,"YYYY"),"FY2024") -> FY2024 | F61: =IFERROR("FY"&TEXT('Data Sheet'!J16,"YYYY"),"FY2025") -> FY2025 | G61: =IFERROR("FY"&TEXT('Data Sheet'!K16,"YYYY"),"FY2026") -> FY2026
B62: Total Debt (₹ Cr) | C62: =C29 -> 6343 | D62: =D29 -> 4794 | E62: =E29 -> 5758 | F62: =F29 -> 6276 | G62: =G29 -> 5215 | I62: Auto-linked from above
B63: Cash & Equivalents | C63: =C45 -> 12636 | D63: =D45 -> 14724 | E63: =E45 -> 20150 | F63: =F45 -> 21289 | G63: =G45 -> 23425 | I63: Auto-linked from above
B64: Investments | C64: =C42 -> 6351 | D64: =D42 -> 5495 | E64: =E42 -> 7137 | F64: =F42 -> 7564 | G64: =G42 -> 7090 | I64: Auto-linked from above
B65: Net Debt (₹ Cr) | C65: =IFERROR(C62-C63-C42,0) -> -12644 | D65: =IFERROR(D62-D63-D42,0) -> -15425 | E65: =IFERROR(E62-E63-E42,0) -> -21529 | F65: =IFERROR(F62-F63-F42,0) -> -22577 | G65: =IFERROR(G62-G63-G42,0) -> -25300 | I65: Total Debt - Cash & Equivalents - Investments
B66: Non-Controlling Interest | C66: =C33 -> 92 | D66: =D33 -> -7 | E66: =E33 -> 8 | F66: =F33 -> 18 | G66: =G33 -> 32 | I66: Auto-linked from above
B67: NWC (Net Working Capital) | C67: =C44+C43-C34-C35 -> 14332 | D67: =D44+D43-D34-D35 -> 19054 | E67: =E44+E43-E34-E35 -> 19695 | F67: =F44+F43-F34-F35 -> 19546 | G67: =G44+G43-G34-G35 -> 16118 | I67: Operating NWC (trade cycle) = Trade Receivables + Inventories - Trade Payables - Advance from Customers. Excludes non-operating "Other" buckets that made the old ratio swing 5.5%-14.4%.
B68: Market Capitalisation (₹ Cr) | C68: 282000 | D68: 397300 | E68: 514800 | F68: 449600 | G68: 315200 | I68: 🔵 MANUAL: CompaniesMarketCap.com → search company → Market Cap History → annual data. Data Sheet only has CURRENT market cap, not historical by year.
B69: Shares Outstanding (Crores) | C69: 271.37 | D69: 271.37 | E69: 271.37 | F69: 271.37 | G69: 271.37 | I69: 🟢 AUTO from Data Sheet row 70 (No. of Equity Shares) ÷ 10,000,000 to convert to Crores. Verify against CompaniesMarketCap.com for accuracy.
B70: Average Debt (₹ Cr) | C70: =C62 -> 6343 | D70: =IFERROR((D62+C62)/2,0) -> 5568.5 | E70: =IFERROR((E62+D62)/2,0) -> 5276 | F70: =IFERROR((F62+E62)/2,0) -> 6017 | G70: =IFERROR((G62+F62)/2,0) -> 5745.5
B71: Interest Expense | C71: =C8 -> 319 | D71: =D8 -> 353 | E71: =E8 -> 553 | F71: =F8 -> 644 | G71: =G8 -> 869 | I71: Auto-linked from above
B72: Average Interest Rate on debt% | C72: =C71/C70 -> 0.05029166 | D72: =D71/D70 -> 0.063392296 | E72: =E71/E70 -> 0.10481425 | F72: =F71/F70 -> 0.10703008 | G72: =G71/G70 -> 0.1512488
B73: Capex (₹ Cr) | C73: =IFERROR(ABS(C57),0) -> 1645 | D73: =IFERROR(ABS(D57),0) -> 1661 | E73: =IFERROR(ABS(E57),0) -> 1048 | F73: =IFERROR(ABS(F57),0) -> 1108 | G73: =IFERROR(ABS(G57),0) -> 1422
B74: FCF — Screener (cross-check) | C74: =C58 -> 15345 | D74: =D58 -> 16565 | E74: =E58 -> 21432 | F74: =F58 -> 21178 | G74: =G58 -> 18576 | I74: Compare with model FCF tab
B76: Screener Label
B77: EBITDA Margin % | C77: =IFERROR(C6/C5,0) -> 0.23968197 | D77: =IFERROR(D6/D5,0) -> 0.22303264 | E77: =IFERROR(E6/E5,0) -> 0.22015594 | F77: =IFERROR(F6/F5,0) -> 0.21788048 | G77: =IFERROR(G6/G5,0) -> 0.20555692 | I77: → TREND formula in Assumptions uses this for FY2029+
B78: D&A / Revenue % | C78: =IFERROR(C9/C5,0) -> 0.050507291 | D78: =IFERROR(D9/D5,0) -> 0.040855149 | E78: =IFERROR(E9/E5,0) -> 0.037966392 | F78: =IFERROR(F9/F5,0) -> 0.034889582 | G78: =IFERROR(G9/G5,0) -> 0.033462933 | I78: → TREND function in Assumptions uses this for FY2029+. IT: D&A rising due to Ind AS 116 leases.
B79: Capex / Revenue % | C79: =IFERROR(ABS(C57)/C5,0) -> 0.019205847 | D79: =IFERROR(ABS(D57)/D5,0) -> 0.016371629 | E79: =IFERROR(ABS(E57)/E5,0) -> 0.0095348139 | F79: =IFERROR(ABS(F57)/F5,0) -> 0.0094656358 | G79: =IFERROR(ABS(G57)/G5,0) -> 0.010926358 | I79: Cross-check for capex assumptions
B80: EBIT Margin % | C80: =IFERROR(C18/C5,0) -> 0.18917467 | D80: =IFERROR(D18/D5,0) -> 0.1821775 | E80: =IFERROR(E18/E5,0) -> 0.18218955 | F80: =IFERROR(F18/F5,0) -> 0.1829909 | G80: =IFERROR(G18/G5,0) -> 0.17209399 | I80: → D&A% = EBITDA% − EBIT%. Derive FY2027-28 D&A% from MS EBIT margin.
B81: NWC/Revenue % | C81: =C67/C5 -> 0.16733021 | D81: =D67/D5 -> 0.18780555 | E81: =E67/E5 -> 0.17918718 | F81: =F67/F5 -> 0.16698133 | G81: =G67/G5 -> 0.12384743
B82: (Unbilled Revenue / Deferred Revenue section removed — WC modelled via NWC % of Revenue approach)

Sheet 🔑 Assumptions
B1: ASSUMPTIONS — IT SERVICES DCF | Yellow = your input | Purple = auto-projected | Teal = IT-specific
B2: Col C = Hist Avg | Cols D-E = FY2027-28 [YELLOW — enter from Trendlyne Forecaster] | Cols F-K = FY2029-34 [PURPLE — auto-calculated]
B4: A. MODEL PARAMETERS
B5: Parameter | C5: Value | D5: Guidance
B6: Company Name | C6: HCL | D6: e.g. Infosys, TCS, HCL Tech, Wipro, Tech Mahindra
B7: NSE Ticker | C7: HCLTECH | D7: e.g. INFY, TCS, HCLTECH, WIPRO, TECHM
B8: IT Sub-Sector | C8: Pure-Play IT Services | D8: Select: Pure-Play IT Services / IT+BPO / Product+Platform / Engineering Services / Diversified IT
B9: Currency / Units | C9: INR — ₹ Crores | D9: INR — ₹ Crores
B10: Last Historical FY | C10: FY2026 | D10: e.g. FY2026
B11: MS Forecast Years | D11: FY2027, FY2028 (from Trendlyne Forecaster / Market Screener analyst consensus)
B12: Auto-Projected Years | D12: FY2029 – FY2034 (formula-driven)
B13: No. of Projection Years | D13: Fixed at 8 (2 analyst + 6 auto). Terminal Value captures FY2035→∞
B14: Terminal Growth Rate g | C14: 0.055 | D14: 5–6% for India large-cap IT. Must be < WACC. IT terminal g typically 5.5% (GDP-linked)
B15: Corporate Tax Rate | C15: =AVERAGE('📊 Hist Data'!D11:G11) -> 0.24689258 | D15: IT-SPECIFIC: Use EFFECTIVE rate from Screener P&L (3-yr avg). Indian IT: 20–23% (SEZ/STPI). Do NOT use 25.2%.
B16: Valuation Date | C16: 46169 | D16: Date of this valuation
B19: B. REVENUE & MARGIN ASSUMPTIONS | Yellow = enter from MarketScreener | Purple = auto-projected formula
B20: Assumption | C20: Hist Avg | D20: FY2027E | E20: FY2028E | F20: FY2029E | G20: FY2030E | H20: FY2031E | I20: FY2032E | J20: FY2033E | K20: FY2034E | R20: Method / Note
B21: Revenue Growth % | C21: =IFERROR(AVERAGE('📊 Hist Data'!D21:G21),0) -> 0.11117053 | D21: 0.0705 | E21: 0.0829 | F21: 0.045 | G21: =IFERROR(F21-(F21-$C$14)/5*(1),0) -> 0.047 | H21: =IFERROR(G21-(G21-$C$14)/5*(2),0) -> 0.0502 | I21: =IFERROR(H21-(H21-$C$14)/5*(3),0) -> 0.05308 | J21: =IFERROR(I21-(I21-$C$14)/5*(4),0) -> 0.054616 | K21: =IFERROR(J21-(J21-$C$14)/5*(5),0) -> 0.055 | R21: FY2027-28: Trendlyne Forecaster → Revenue Growth % estimate. IT large-cap: 8-15%. FY2029-34: Linear taper from FY2028 to terminal g.
B22: EBITDA Margin % | C22: =IFERROR(AVERAGE('📊 Hist Data'!C77:G77),0) -> 0.22126159 | D22: 0.2139 | E22: 0.2105 | F22: =IFERROR(E22+(E22-D22)*0.5,0) -> 0.2088 | G22: =IFERROR(F22+(E22-D22)/3,0) -> 0.20766667 | H22: =IFERROR(G22+(E22-D22)/4,0) -> 0.20681667 | I22: =IFERROR(H22+(E22-D22)/5,0) -> 0.20613667 | J22: =IFERROR(I22+(E22-D22)/6,0) -> 0.20557 | K22: =IFERROR(J22+(E22-D22)/7,0) -> 0.20508429 | R22: FY2027-28: Trendlyne EBITDA Margin estimate. IT benchmarks: TCS ~27%, Infosys ~24%, HCL ~20%. FY2029-34: TREND function extrapolation.
B23: D&A / Revenue % | C23: =IFERROR(AVERAGE('📊 Hist Data'!C78:G78),0) -> 0.039536269 | D23: =(297944-251299)/1393184 -> 0.033480861 | E23: =(317627-269042)/1508630 -> 0.032204716 | F23: =IFERROR(D23+(E23-D23)*0.5,0) -> 0.032842788 | G23: =IFERROR(F23+(E23-D23)*0.4,0) -> 0.03233233 | H23: =IFERROR(G23+(E23-D23)*0.3,0) -> 0.031949486 | I23: =IFERROR(H23+(E23-D23)*0.2,0) -> 0.031694257 | J23: =IFERROR(I23+(E23-D23)*0.1,0) -> 0.031566643 | K23: =IFERROR(J23,0) -> 0.031566643 | R23: IT-SPECIFIC: D&A trending UP (Ind AS 116 leases). FY2027-28: derive as (EBITDA% - EBIT%) from Trendlyne. FY2029-34: TREND extrapolation.
B24: EBIT Margin % (formula — auto) | C24: =IFERROR(AVERAGE('📊 Hist Data'!C80:G80),0) -> 0.18172532 | D24: =IFERROR(D22-D23,0) -> 0.18041914 | E24: =IFERROR(E22-E23,0) -> 0.17829528 | F24: =IFERROR(F22-F23,0) -> 0.17595721 | G24: =IFERROR(G22-G23,0) -> 0.17533434 | H24: =IFERROR(H22-H23,0) -> 0.17486718 | I24: =IFERROR(I22-I23,0) -> 0.17444241 | J24: =IFERROR(J22-J23,0) -> 0.17400336 | K24: =IFERROR(K22-K23,0) -> 0.17351764 | R24: Auto-calculated: EBITDA Margin% − D&A%. Do not edit.
B27: C. CAPEX ASSUMPTIONS — IT-SPECIFIC | Enter as % of Revenue (not ₹ Cr) | FY2029+ held flat
B28: Assumption | C28: Hist Avg | D28: FY2027E | E28: FY2028E | F28: FY2029E | G28: FY2030E | H28: FY2031E | I28: FY2032E | J28: FY2033E | K28: FY2034E | R28: Method / Note
B29: Capex / Revenue % ← ENTER THIS | C29: =IFERROR(AVERAGE('📊 Hist Data'!C79:G79),0) -> 0.013100857 | D29: =37520/1393184 -> 0.026931116 | E29: =38276/1508630 -> 0.025371363 | F29: =AVERAGE(C29:E29) -> 0.021801112 | G29: =$F$29 -> 0.021801112 | H29: =$F$29 -> 0.021801112 | I29: =$F$29 -> 0.021801112 | J29: =$F$29 -> 0.021801112 | K29: =$F$29 -> 0.021801112 | R29: IT-SPECIFIC DRIVER. Enter Capex as % of Revenue. FY2029-34: held flat at FY2028 rate. Benchmarks: TCS 1.5%, Infosys 2%, HCL 2.5%. Source: Trendlyne capex ÷ revenue estimate.
B30: Total Capex (₹ Cr) ← auto-derived | C30: =IFERROR(AVERAGE('📊 Hist Data'!C73:G73),0) -> 1376.8 | D30: =IFERROR(D29*'📈 Projections'!D5,0) -> 3752.0203 | E30: =IFERROR(E29*'📈 Projections'!E5,0) -> 3827.7449 | F30: =IFERROR(F29*'📈 Projections'!F5,0) -> 3437.1154 | G30: =IFERROR(G29*'📈 Projections'!G5,0) -> 3598.6598 | H30: =IFERROR(H29*'📈 Projections'!H5,0) -> 3779.3126 | I30: =IFERROR(I29*'📈 Projections'!I5,0) -> 3979.9185 | J30: =IFERROR(J29*'📈 Projections'!J5,0) -> 4197.2857 | K30: =IFERROR(K29*'📈 Projections'!K5,0) -> 4428.1364 | R30: Auto-derived: Capex% × Projected Revenue. Do not edit directly.
B33: D. WORKING CAPITAL — NWC % OF REVENUE | NWC = NWC% × Revenue | ΔWC = Year N − Year N-1 | NWC% scales revenue growth automatically
B34: Metric | C34: Hist 5Y Avg | D34: FY2027E | E34: FY2028E | F34: FY2029E | G34: FY2030E | H34: FY2031E | I34: FY2032E | J34: FY2033E | K34: FY2034E | R34: Source / Notes
B35: Historical simple aveage of NWC % of Revenue | C35: =AVERAGE('📊 Hist Data'!C81:G81) -> 0.16503034 | R35: Auto from Hist Data. NWC = (Trade Rec + Inventories + Other CA) − (Trade Payables + Advance from Customers + Other CL). Watch the trend — declining NWC% = improving cash efficiency.
B36: ⭐ Projected NWC % (Weighted Average) | C36: =SUMPRODUCT(C38:$G$38,'📊 Hist Data'!C81:G81)/SUM('🔑 Assumptions'!$C$38:$G$38) -> 0.15784436 | D36: =IFERROR($C$36,0) -> 0.15784436 | E36: =IFERROR(D36,0) -> 0.15784436 | F36: =IFERROR($E$36,0) -> 0.15784436 | G36: =IFERROR($E$36,0) -> 0.15784436 | H36: =IFERROR($E$36,0) -> 0.15784436 | I36: =IFERROR($E$36,0) -> 0.15784436 | J36: =IFERROR($E$36,0) -> 0.15784436 | K36: =IFERROR($E$36,0) -> 0.15784436 | R36: FY2027-28: Enter from Trendlyne WC data OR keep at hist avg. FY2029+: AUTO — flat at FY2028 level. How to get NWC%: Screener.in → company page → scroll to "Working Capital" in ratios box → divide by Sales for that year. HCL hist avg ~9.7%, 3Y avg ~7%. WSS model uses 9.55%.
B37: Historical Years(N ----> Most recent year) | C37: FY_N-4 | D37: FY_N-3 | E37: FY_N-2 | F37: FY_N-1 | G37: FY_N
B38: Weights | C38: 1 | D38: 2 | E38: 3 | F38: 4 | G38: 5 | I38: Note: Default: 1,2,3,4,5 — increase FY_N weight to give more emphasis to most recent year
B52: F. WACC — 4 Steps | Ke = Rf + β×ERP | Kd = IntExp÷AvgDebt×(1-t) | WACC = Ke×E% + Kd×D%
B53: Component | C53: Value | D53: Formula / Source
B54: ── STEP 1: COST OF EQUITY Ke = Rf + β × ERP ──
B55: Risk-Free Rate Rf (%) | C55: 0.071 | D55: 10Y G-Sec yield. Source: investing.com → search "India 10 Year Bond Yield" → current yield. OR RBI website → Government Securities. Current (May 2026): ~7.0-7.1%.
B56: Equity Risk Premium ERP (%) | C56: 0.0726 | D56: Damodaran India ERP. Source: pages.stern.nyu.edu/~adamodar → click "Implied ERP" → India row. Updated monthly. Current India ERP: ~7.0-7.5%.
B57: Beta — Current (β) | C57: =IFERROR('📐 Beta Calc'!C6,1) -> 0.91809063 | D57: Auto-linked from Beta Calc tab. SLOPE(stock weekly returns, Nifty50 returns) over 3Y. IT large-cap: TCS ~0.7, Infosys ~0.8, HCL ~0.9, Wipro ~0.9.
B58: Beta — At Maturity (β_m) | C58: 1 | D58: Stable-state beta. IT large-cap: 0.8–1.0 (defensive growth). Mid-cap IT: 0.9–1.1. Use 1.0 if uncertain. Conservative for IT.
B59: Cost of Equity — Current Ke | C59: =IFERROR(C55+C57*C56,0) -> 0.13765338
B60: Cost of Equity — Maturity Ke_m | C60: =IFERROR(C55+C58*C56,0) -> 0.1436
B62: ── STEP 2: COST OF DEBT Kd = IntExp ÷ AvgDebt × (1−t) ──
B63: Interest Expense (₹ Cr) | C63: =IFERROR('📊 Hist Data'!G71,0) -> 869 | D63: Auto-linked from Hist Data → last year Interest Expense
B64: Average Debt (₹ Cr) | C64: =IFERROR('📊 Hist Data'!G70,0) -> 5745.5 | D64: Auto-linked from Hist Data → last year Average Debt
B65: Pre-Tax Cost of Debt Kd_pre | C65: =IFERROR(C63/C64,0.085) -> 0.1512488
B66: Post-Tax Cost of Debt Kd | C66: =IFERROR(C65*(1-$C$15),0) -> 0.1139066
B68: ── STEP 3: CAPITAL STRUCTURE E/(D+E) and D/(D+E) ──
B69: Market Capitalisation (₹ Cr) | C69: =IFERROR('📊 Hist Data'!G68,0) -> 315200 | D69: Auto-linked from Hist Data → latest year Market Cap. Source: CompaniesMarketCap.com
B70: Total Debt (₹ Cr) | C70: =IFERROR('📊 Hist Data'!G62,0) -> 5215 | D70: Auto-linked from Hist Data → latest year Total Debt
B71: Equity Weight E/(D+E) % | C71: =IFERROR(C69/(C69+C70),0.6) -> 0.98372423
B72: Debt Weight D/(D+E) % | C72: =IFERROR(1-C71,0.4) -> 0.016275767
B74: ── STEP 4: WACC ──
B75: WACC — High Growth Phase % | C75: =IFERROR(C59*C71+C66*C72,0) -> 0.13726688
B76: WACC — Terminal Phase % | C76: =IFERROR(C60*C71+C66*C72*0.98,0) -> 0.14307964
B77: WACC − g (must be > 0) | C77: =IFERROR(C76-C14,0) -> 0.088079639
B80: G. OTHER INCOME (TREASURY) — IT-SPECIFIC | Model as Cash × Yield%, not flat carry-forward
B81: Component | C81: Value | D81: Formula / Source
B82: Treasury Yield Assumption % | C82: 0.065 | D82: Assumed return on cash pile. Use ~6.5% (liquid fund / FD blend). Source: SBI FD rates ~7% or NIFTY Liquid Fund ~6.5%.
B83: Other Income Method | C83: Cash × Yield % | D83: Projected Other Income = Prior Year Net Cash Balance × Treasury Yield %. As FCF accumulates, cash grows → Other Income grows automatically.
B86: H. VALUATION BRIDGE INPUTS (latest year balance sheet items)
B87: Input | C87: Value | D87: Source
B88: Total Debt (₹ Cr) | C88: =IFERROR('📊 Hist Data'!G62,0) -> 5215 | D88: Auto: Hist Data → Total Debt last year
B89: Cash & Equivalents (₹ Cr) | C89: =IFERROR('📊 Hist Data'!G63,0) -> 23425 | D89: Auto: Hist Data → Cash last year
B90: Investments (non-operating) (₹ Cr) | C90: 7090 | D90: Manual: Screener BS → 'Investments' row, last year. Non-operating investments only.
B91: Non-Controlling Interest (₹ Cr) | C91: =IFERROR('📊 Hist Data'!G66,0) -> 32 | D91: Auto: Hist Data → NCI last year
B92: Shares Outstanding (Crores) | C92: =IFERROR('📊 Hist Data'!G69,0) -> 271.37 | D92: Auto: Hist Data → Shares last year. Source: CompaniesMarketCap.com
B93: Current Market Price (₹/share) | C93: 1165 | D93: ⚠ Manual: today's CMP from NSE/BSE/Google. Update every valuation.
B95: Net Cash / (Net Debt) [+ = IT is net cash] | C95: =IFERROR(C89-C88-C90,0) -> 11120 | D95: If POSITIVE → company is net cash (typical for TCS, Infosys). Equity Value > Enterprise Value. If negative → net debt.

Sheet 📈 Projections
B1: PROJECTED FINANCIALS — IT SERVICES (₹ Crores) | All formulas — do not edit
B2: Col C = FY2026 actual (linked from Hist Data). Cols D-E = FY2027-28 (formula from yellow assumptions). Cols F-K = FY2029-34 (purple auto-formula). All cells are formulas — do not type here.
B3: PROJECTED P&L
B4: Line Item | C4: FY2026A | D4: FY2027E | E4: FY2028E | F4: FY2029E | G4: FY2030E | H4: FY2031E | I4: FY2032E | J4: FY2033E | K4: FY2034E
B5: Net Revenue (₹ Cr) | C5: =IFERROR('📊 Hist Data'!G5,0) -> 130144 | D5: =C5*(1+D6) -> 139319.15 | E5: =D5*(1+E6) -> 150868.71 | F5: =E5*(1+F6) -> 157657.8 | G5: =F5*(1+G6) -> 165067.72 | H5: =G5*(1+H6) -> 173354.12 | I5: =H5*(1+I6) -> 182555.75 | J5: =I5*(1+J6) -> 192526.22 | K5: =J5*(1+K6) -> 203115.16
B6: Revenue Growth % | C6: =IFERROR('📊 Hist Data'!G21,0) -> 0.11181923 | D6: ='🔑 Assumptions'!D21 -> 0.0705 | E6: ='🔑 Assumptions'!E21 -> 0.0829 | F6: ='🔑 Assumptions'!F21 -> 0.045 | G6: ='🔑 Assumptions'!G21 -> 0.047 | H6: ='🔑 Assumptions'!H21 -> 0.0502 | I6: ='🔑 Assumptions'!I21 -> 0.05308 | J6: ='🔑 Assumptions'!J21 -> 0.054616 | K6: ='🔑 Assumptions'!K21 -> 0.055
B7: EBITDA (₹ Cr) | C7: =IFERROR('📊 Hist Data'!G6,0) -> 26752 | D7: =D5*D8 -> 29800.367 | E7: =E5*E8 -> 31757.863 | F7: =F5*F8 -> 32918.949 | G7: =G5*G8 -> 34279.063 | H7: =H5*H8 -> 35852.521 | I7: =I5*I8 -> 37631.435 | J7: =J5*J8 -> 39577.615 | K7: =K5*K8 -> 41655.728
B8: EBITDA Margin % | C8: =IFERROR('📊 Hist Data'!G77,0) -> 0.20555692 | D8: ='🔑 Assumptions'!D22 -> 0.2139 | E8: ='🔑 Assumptions'!E22 -> 0.2105 | F8: ='🔑 Assumptions'!F22 -> 0.2088 | G8: ='🔑 Assumptions'!G22 -> 0.20766667 | H8: ='🔑 Assumptions'!H22 -> 0.20681667 | I8: ='🔑 Assumptions'!I22 -> 0.20613667 | J8: ='🔑 Assumptions'!J22 -> 0.20557 | K8: ='🔑 Assumptions'!K22 -> 0.20508429
B9: Depreciation & Amortisation (₹ Cr) | C9: =IFERROR('📊 Hist Data'!G9,0) -> 4355 | D9: =IFERROR(D5*'🔑 Assumptions'!D23,0) -> 4664.5252 | E9: =IFERROR(E5*'🔑 Assumptions'!E23,0) -> 4858.6839 | F9: =IFERROR(F5*'🔑 Assumptions'!F23,0) -> 5177.9218 | G9: =IFERROR(G5*'🔑 Assumptions'!G23,0) -> 5337.024 | H9: =IFERROR(H5*'🔑 Assumptions'!H23,0) -> 5538.575 | I9: =IFERROR(I5*'🔑 Assumptions'!I23,0) -> 5785.9691 | J9: =IFERROR(J5*'🔑 Assumptions'!J23,0) -> 6077.4064 | K9: =IFERROR(K5*'🔑 Assumptions'!K23,0) -> 6411.6637
B10: EBIT (₹ Cr) | C10: =IFERROR('📊 Hist Data'!G80*'📊 Hist Data'!G5,0) -> 22397 | D10: =IFERROR(D7-D9,0) -> 25135.841 | E10: =IFERROR(E7-E9,0) -> 26899.18 | F10: =IFERROR(F7-F9,0) -> 27741.027 | G10: =IFERROR(G7-G9,0) -> 28942.039 | H10: =IFERROR(H7-H9,0) -> 30313.946 | I10: =IFERROR(I7-I9,0) -> 31845.466 | J10: =IFERROR(J7-J9,0) -> 33500.209 | K10: =IFERROR(K7-K9,0) -> 35244.064
B11: EBIT Margin % | C11: =IFERROR('📊 Hist Data'!G80,0) -> 0.17209399 | D11: =IFERROR(D10/D5,0) -> 0.18041914 | E11: =IFERROR(E10/E5,0) -> 0.17829528 | F11: =IFERROR(F10/F5,0) -> 0.17595721 | G11: =IFERROR(G10/G5,0) -> 0.17533434 | H11: =IFERROR(H10/H5,0) -> 0.17486718 | I11: =IFERROR(I10/I5,0) -> 0.17444241 | J11: =IFERROR(J10/J5,0) -> 0.17400336 | K11: =IFERROR(K10/K5,0) -> 0.17351764
B12: Interest Expense (₹ Cr) | C12: =IFERROR('📊 Hist Data'!G8,0) -> 869 | D12: =$C$12 -> 869 | E12: =$C$12 -> 869 | F12: =$C$12 -> 869 | G12: =$C$12 -> 869 | H12: =$C$12 -> 869 | I12: =$C$12 -> 869 | J12: =$C$12 -> 869 | K12: =$C$12 -> 869
B13: Other Income (₹ Cr) | C13: =IFERROR(ABS('📊 Hist Data'!G7),0) -> 574 | D13: =IFERROR(ABS(C13)*1.03,0) -> 591.22 | E13: =IFERROR(ABS(D13)*1.03,0) -> 608.9566 | F13: =IFERROR(ABS(E13)*1.03,0) -> 627.2253 | G13: =IFERROR(ABS(F13)*1.03,0) -> 646.04206 | H13: =IFERROR(ABS(G13)*1.03,0) -> 665.42332 | I13: =IFERROR(ABS(H13)*1.03,0) -> 685.38602 | J13: =IFERROR(ABS(I13)*1.03,0) -> 705.9476 | K13: =IFERROR(ABS(J13)*1.03,0) -> 727.12603 | L13: ⚠ IT NOTE: If company has large cash pile (>₹10,000 Cr), consider modelling as: Cash Balance × Treasury Yield (Assumptions G). Currently carries forward historical Other Income with growth.
B14: PBT (₹ Cr) | C14: =IFERROR('📊 Hist Data'!G10,0) -> 22102 | D14: =IFERROR(D10-D12+D13,0) -> 24858.061 | E14: =IFERROR(E10-E12+E13,0) -> 26639.136 | F14: =IFERROR(F10-F12+F13,0) -> 27499.252 | G14: =IFERROR(G10-G12+G13,0) -> 28719.081 | H14: =IFERROR(H10-H12+H13,0) -> 30110.369 | I14: =IFERROR(I10-I12+I13,0) -> 31661.852 | J14: =IFERROR(J10-J12+J13,0) -> 33337.156 | K14: =IFERROR(K10-K12+K13,0) -> 35102.19
B15: Tax Expense (₹ Cr) | C15: =IFERROR('📊 Hist Data'!G12,0) -> 5450 | D15: =MAX(0,'🔑 Assumptions'!$C$15*D14) -> 6137.271 | E15: =MAX(0,'🔑 Assumptions'!$C$15*E14) -> 6577.0051 | F15: =MAX(0,'🔑 Assumptions'!$C$15*F14) -> 6789.3615 | G15: =MAX(0,'🔑 Assumptions'!$C$15*G14) -> 7090.5281 | H15: =MAX(0,'🔑 Assumptions'!$C$15*H14) -> 7434.0268 | I15: =MAX(0,'🔑 Assumptions'!$C$15*I14) -> 7817.0764 | J15: =MAX(0,'🔑 Assumptions'!$C$15*J14) -> 8230.6966 | K15: =MAX(0,'🔑 Assumptions'!$C$15*K14) -> 8666.4704
B16: Effective Tax Rate % | C16: =IFERROR('📊 Hist Data'!G13,0) -> 0.24658402 | D16: =IFERROR(D15/D14,0) -> 0.24689258 | E16: =IFERROR(E15/E14,0) -> 0.24689258 | F16: =IFERROR(F15/F14,0) -> 0.24689258 | G16: =IFERROR(G15/G14,0) -> 0.24689258 | H16: =IFERROR(H15/H14,0) -> 0.24689258 | I16: =IFERROR(I15/I14,0) -> 0.24689258 | J16: =IFERROR(J15/J14,0) -> 0.24689258 | K16: =IFERROR(K15/K14,0) -> 0.24689258
B17: PAT (₹ Cr) | C17: =IFERROR('📊 Hist Data'!G14,0) -> 16642 | D17: =IFERROR(D14-D15,0) -> 18720.79 | E17: =IFERROR(E14-E15,0) -> 20062.131 | F17: =IFERROR(F14-F15,0) -> 20709.891 | G17: =IFERROR(G14-G15,0) -> 21628.553 | H17: =IFERROR(H14-H15,0) -> 22676.342 | I17: =IFERROR(I14-I15,0) -> 23844.775 | J17: =IFERROR(J14-J15,0) -> 25106.46 | K17: =IFERROR(K14-K15,0) -> 26435.72
B18: PAT to Equity Margin % | C18: =IFERROR('📊 Hist Data'!G20,0) -> 0.1277969 | D18: =D20/D5 -> 0.13429805 | E18: =E20/E5 -> 0.13290434 | F18: =F20/F5 -> 0.13128633 | G18: =G20/G5 -> 0.13095473 | H18: =H20/H5 -> 0.13073574 | I18: =I20/I5 -> 0.13054299 | J18: =J20/J5 -> 0.13033232 | K18: =K20/K5 -> 0.13007865
B19: Minority Interest (₹ Cr) | C19: =IFERROR(ABS('📊 Hist Data'!G15),0) -> 10 | D19: =IFERROR(C19*1.05,0) -> 10.5 | E19: =IFERROR(D19*1.05,0) -> 11.025 | F19: =IFERROR(E19*1.05,0) -> 11.57625 | G19: =IFERROR(F19*1.05,0) -> 12.155063 | H19: =IFERROR(G19*1.05,0) -> 12.762816 | I19: =IFERROR(H19*1.05,0) -> 13.400956 | J19: =IFERROR(I19*1.05,0) -> 14.071004 | K19: =IFERROR(J19*1.05,0) -> 14.774554
B20: PAT to Equity (₹ Cr) | C20: =IFERROR('📊 Hist Data'!G16,0) -> 16632 | D20: =IFERROR(D17-D19,0) -> 18710.29 | E20: =IFERROR(E17-E19,0) -> 20051.106 | F20: =IFERROR(F17-F19,0) -> 20698.315 | G20: =IFERROR(G17-G19,0) -> 21616.398 | H20: =IFERROR(H17-H19,0) -> 22663.579 | I20: =IFERROR(I17-I19,0) -> 23831.374 | J20: =IFERROR(J17-J19,0) -> 25092.389 | K20: =IFERROR(K17-K19,0) -> 26420.945
B23: WORKING CAPITAL SCHEDULE | NWC = NWC% × Revenue | ΔWC feeds FCFF directly
B24: Line Item | C24: FY2026A | D24: FY2027E | E24: FY2028E | F24: FY2029E | G24: FY2030E | H24: FY2031E | I24: FY2032E | J24: FY2033E | K24: FY2034E
B25: Net Revenue (₹ Cr) [linked from P&L above] | C25: =C5 -> 130144 | D25: =D5 -> 139319.15 | E25: =E5 -> 150868.71 | F25: =F5 -> 157657.8 | G25: =G5 -> 165067.72 | H25: =H5 -> 173354.12 | I25: =I5 -> 182555.75 | J25: =J5 -> 192526.22 | K25: =K5 -> 203115.16
B26: NWC % of Revenue [from Assumptions D] | C26: =IFERROR(('📊 Hist Data'!G44+'📊 Hist Data'!G43-'📊 Hist Data'!G34-'📊 Hist Data'!G35)/'📊 Hist Data'!G5,0) -> 0.12384743 | D26: =IFERROR('🔑 Assumptions'!D36,0) -> 0.15784436 | E26: =IFERROR('🔑 Assumptions'!E36,0) -> 0.15784436 | F26: =IFERROR('🔑 Assumptions'!F36,0) -> 0.15784436 | G26: =IFERROR('🔑 Assumptions'!G36,0) -> 0.15784436 | H26: =IFERROR('🔑 Assumptions'!H36,0) -> 0.15784436 | I26: =IFERROR('🔑 Assumptions'!I36,0) -> 0.15784436 | J26: =IFERROR('🔑 Assumptions'!J36,0) -> 0.15784436 | K26: =IFERROR('🔑 Assumptions'!K36,0) -> 0.15784436
B27: ⭐ Net Working Capital (₹ Cr) = NWC% × Revenue | C27: =IFERROR('📊 Hist Data'!G44+'📊 Hist Data'!G43-'📊 Hist Data'!G34-'📊 Hist Data'!G35,0) -> 16118 | D27: =IFERROR(D26*D25,0) -> 21990.742 | E27: =IFERROR(E26*E25,0) -> 23813.774 | F27: =IFERROR(F26*F25,0) -> 24885.394 | G27: =IFERROR(G26*G25,0) -> 26055.008 | H27: =IFERROR(H26*H25,0) -> 27362.969 | I27: =IFERROR(I26*I25,0) -> 28815.395 | J27: =IFERROR(J26*J25,0) -> 30389.177 | K27: =IFERROR(K26*K25,0) -> 32060.582
B34: ⭐ ΔWC — Change in Working Capital (₹ Cr) | feeds FCFF | C34: "-" | D34: =IFERROR(D26*(D25-C25),0) -> 1448.246 | E34: =IFERROR(E26*(E25-D25),0) -> 1823.0325 | F34: =IFERROR(F26*(F25-E25),0) -> 1071.6198 | G34: =IFERROR(G26*(G25-F25),0) -> 1169.6135 | H34: =IFERROR(H26*(H25-G25),0) -> 1307.9614 | I34: =IFERROR(I26*(I25-H25),0) -> 1452.4264 | J34: =IFERROR(J26*(J25-I25),0) -> 1573.7816 | K34: =IFERROR(K26*(K25-J25),0) -> 1671.4047 | L34: → This row feeds directly into FCF & Val Part 1 row 10. With NWC% flat, ΔWC ≈ NWC% × Revenue Growth. For HCL at 9.7% NWC% growing 7%/yr: ΔWC ≈ ~960 Cr/yr initially.

Sheet 💰 FCF & Val
B1: FREE CASH FLOW TO FIRM + DCF VALUATION — IT SERVICES (₹ Crores)
B3: PART 1 — FCFF = NOPAT + D&A − Capex − ΔWC
B4: Line Item | D4: FY2027E | E4: FY2028E | F4: FY2029E | G4: FY2030E | H4: FY2031E | I4: FY2032E | J4: FY2033E | K4: FY2034E
B5: EBIT (₹ Cr) | D5: =IFERROR('📈 Projections'!D10,0) -> 25135.841 | E5: =IFERROR('📈 Projections'!E10,0) -> 26899.18 | F5: =IFERROR('📈 Projections'!F10,0) -> 27741.027 | G5: =IFERROR('📈 Projections'!G10,0) -> 28942.039 | H5: =IFERROR('📈 Projections'!H10,0) -> 30313.946 | I5: =IFERROR('📈 Projections'!I10,0) -> 31845.466 | J5: =IFERROR('📈 Projections'!J10,0) -> 33500.209 | K5: =IFERROR('📈 Projections'!K10,0) -> 35244.064
B6: Tax on EBIT (EBIT × Tax Rate) | D6: =IFERROR(D5*'🔑 Assumptions'!$C$15,0) -> 6205.8528 | E6: =IFERROR(E5*'🔑 Assumptions'!$C$15,0) -> 6641.2079 | F6: =IFERROR(F5*'🔑 Assumptions'!$C$15,0) -> 6849.0539 | G6: =IFERROR(G5*'🔑 Assumptions'!$C$15,0) -> 7145.5747 | H6: =IFERROR(H5*'🔑 Assumptions'!$C$15,0) -> 7484.2884 | I6: =IFERROR(I5*'🔑 Assumptions'!$C$15,0) -> 7862.4093 | J6: =IFERROR(J5*'🔑 Assumptions'!$C$15,0) -> 8270.953 | K6: =IFERROR(K5*'🔑 Assumptions'!$C$15,0) -> 8701.498
B7: NOPAT — Net Operating Profit After Tax | D7: =IFERROR(D5-D6,0) -> 18929.989 | E7: =IFERROR(E5-E6,0) -> 20257.972 | F7: =IFERROR(F5-F6,0) -> 20891.973 | G7: =IFERROR(G5-G6,0) -> 21796.464 | H7: =IFERROR(H5-H6,0) -> 22829.657 | I7: =IFERROR(I5-I6,0) -> 23983.056 | J7: =IFERROR(J5-J6,0) -> 25229.256 | K7: =IFERROR(K5-K6,0) -> 26542.566
B8: + Depreciation & Amortisation | D8: =IFERROR('📈 Projections'!D9,0) -> 4664.5252 | E8: =IFERROR('📈 Projections'!E9,0) -> 4858.6839 | F8: =IFERROR('📈 Projections'!F9,0) -> 5177.9218 | G8: =IFERROR('📈 Projections'!G9,0) -> 5337.024 | H8: =IFERROR('📈 Projections'!H9,0) -> 5538.575 | I8: =IFERROR('📈 Projections'!I9,0) -> 5785.9691 | J8: =IFERROR('📈 Projections'!J9,0) -> 6077.4064 | K8: =IFERROR('📈 Projections'!K9,0) -> 6411.6637
B9: − Total Capex | D9: ='🔑 Assumptions'!D30 -> 3752.0203 | E9: ='🔑 Assumptions'!E30 -> 3827.7449 | F9: ='🔑 Assumptions'!F30 -> 3437.1154 | G9: ='🔑 Assumptions'!G30 -> 3598.6598 | H9: ='🔑 Assumptions'!H30 -> 3779.3126 | I9: ='🔑 Assumptions'!I30 -> 3979.9185 | J9: ='🔑 Assumptions'!J30 -> 4197.2857 | K9: ='🔑 Assumptions'!K30 -> 4428.1364
B10: − ΔWC (Change in Working Capital) | + ΔWC = cash used; − ΔWC = cash released | D10: =IFERROR('📈 Projections'!D34,0) -> 1448.246 | E10: =IFERROR('📈 Projections'!E34,0) -> 1823.0325 | F10: =IFERROR('📈 Projections'!F34,0) -> 1071.6198 | G10: =IFERROR('📈 Projections'!G34,0) -> 1169.6135 | H10: =IFERROR('📈 Projections'!H34,0) -> 1307.9614 | I10: =IFERROR('📈 Projections'!I34,0) -> 1452.4264 | J10: =IFERROR('📈 Projections'!J34,0) -> 1573.7816 | K10: =IFERROR('📈 Projections'!K34,0) -> 1671.4047
B11: FREE CASH FLOW TO FIRM (FCFF) | D11: =IFERROR(D7+D8-D9-D10,0) -> 18394.248 | E11: =IFERROR(E7+E8-E9-E10,0) -> 19465.878 | F11: =IFERROR(F7+F8-F9-F10,0) -> 21561.16 | G11: =IFERROR(G7+G8-G9-G10,0) -> 22365.215 | H11: =IFERROR(H7+H8-H9-H10,0) -> 23280.958 | I11: =IFERROR(I7+I8-I9-I10,0) -> 24336.681 | J11: =IFERROR(J7+J8-J9-J10,0) -> 25535.595 | K11: =IFERROR(K7+K8-K9-K10,0) -> 26854.689
B12: FCFF Growth % | D12: "-" | E12: =IFERROR((E11-D11)/D11,0) -> 0.058259004 | F12: =IFERROR((F11-E11)/E11,0) -> 0.1076387 | G12: =IFERROR((G11-F11)/F11,0) -> 0.037291819 | H12: =IFERROR((H11-G11)/G11,0) -> 0.040945001 | I12: =IFERROR((I11-H11)/H11,0) -> 0.045347019 | J12: =IFERROR((J11-I11)/I11,0) -> 0.049263663 | K12: =IFERROR((K11-J11)/J11,0) -> 0.051657073
B14: PART 2 — DISCOUNTING PV = FCFF ÷ (1+WACC)^n
B15: Line Item | D15: FY2027E | E15: FY2028E | F15: FY2029E | G15: FY2030E | H15: FY2031E | I15: FY2032E | J15: FY2033E | K15: FY2034E
B16: Year Number | D16: 1 | E16: 2 | F16: 3 | G16: 4 | H16: 5 | I16: 6 | J16: 7 | K16: 8
B17: WACC — High Growth % | D17: ='🔑 Assumptions'!$C$75 -> 0.13726688 | E17: ='🔑 Assumptions'!$C$75 -> 0.13726688 | F17: ='🔑 Assumptions'!$C$75 -> 0.13726688 | G17: ='🔑 Assumptions'!$C$75 -> 0.13726688 | H17: ='🔑 Assumptions'!$C$75 -> 0.13726688 | I17: ='🔑 Assumptions'!$C$75 -> 0.13726688 | J17: ='🔑 Assumptions'!$C$75 -> 0.13726688 | K17: ='🔑 Assumptions'!$C$75 -> 0.13726688
B18: Discount Factor 1÷(1+WACC)^n | D18: =IFERROR(1/(1+D17)^D16,0) -> 0.87930108 | E18: =IFERROR(1/(1+E17)^E16,0) -> 0.77317039 | F18: =IFERROR(1/(1+F17)^F16,0) -> 0.67984956 | G18: =IFERROR(1/(1+G17)^G16,0) -> 0.59779246 | H18: =IFERROR(1/(1+H17)^H16,0) -> 0.52563955 | I18: =IFERROR(1/(1+I17)^I16,0) -> 0.46219543 | J18: =IFERROR(1/(1+J17)^J16,0) -> 0.40640894 | K18: =IFERROR(1/(1+K17)^K16,0) -> 0.35735582
B19: Present Value of FCFF (₹ Cr) | D19: =IFERROR(D11*D18,0) -> 16174.082 | E19: =IFERROR(E11*E18,0) -> 15050.441 | F19: =IFERROR(F11*F18,0) -> 14658.345 | G19: =IFERROR(G11*G18,0) -> 13369.757 | H19: =IFERROR(H11*H18,0) -> 12237.393 | I19: =IFERROR(I11*I18,0) -> 11248.302 | J19: =IFERROR(J11*J18,0) -> 10377.894 | K19: =IFERROR(K11*K18,0) -> 9596.6793
B21: PART 3 — TERMINAL VALUE TV = FCFF(N+1) ÷ (WACC_tv − g) | Captures FY2035 → ∞
B22: FCFF in Terminal Year (FY2034) (₹ Cr) | C22: =IFERROR(K11,0) -> 26854.689
B23: Terminal Growth Rate g (%) | C23: ='🔑 Assumptions'!$C$14 -> 0.055
B24: WACC — Terminal Phase (%) | C24: ='🔑 Assumptions'!C76 -> 0.14307964
B25: FCFF Year N+1 (FY2035) (₹ Cr) | C25: =IFERROR(C22*(1+C23),0) -> 28331.697
B26: TERMINAL VALUE (₹ Cr) — FY2035→∞ | C26: =IFERROR(C25/(C24-C23),0) -> 321660
B27: Discount Factor (Year 8) | C27: =IFERROR(K18,0) -> 0.35735582
B28: PV of Terminal Value (₹ Cr) | C28: =IFERROR(C26*C27,0) -> 114947.07
B30: ⚠ IT NOTE: Most large IT companies are NET CASH (Cash > Debt). If Net Debt (Debt - Cash) is NEGATIVE, the equity bridge ADDS net cash to EV. Check: if Total Debt < Cash & Equivalents, your Equity Value > Enterprise Value. This is correct.
B32: PART 4 — ENTERPRISE VALUE → EQUITY VALUE BRIDGE
B33: Sum of PV of FCFs (₹ Cr) | C33: =IFERROR(D19+E19+F19+G19+H19+I19+J19+K19,0) -> 102712.89
B34: PV of Terminal Value (₹ Cr) | C34: =C28 -> 114947.07
B35: ENTERPRISE VALUE (₹ Cr) | C35: =C33+C34 -> 217659.97
B36: Net Cash / (Net Debt) [+ = net cash, − = net debt] | C36: ='🔑 Assumptions'!C89-'🔑 Assumptions'!C88 -> 18210
B38: Less: Total Debt (₹ Cr) | C38: ='🔑 Assumptions'!$C$70 -> 5215
B39: Less: Non-Controlling Interest (₹ Cr) | C39: ='🔑 Assumptions'!C91 -> 32
B40: Add: Cash & Equivalents (₹ Cr) | C40: ='🔑 Assumptions'!C89 -> 23425
B41: Add: Investments (₹ Cr) | C41: ='🔑 Assumptions'!$C$90 -> 7090
B42: DCF VALUE OF EQUITY (₹ Cr) | C42: =C35-C38-C39+C40+C41 -> 242927.97
B44: Shares Outstanding (Crores) | C44: ='📊 Hist Data'!G69 -> 271.37
B45: INTRINSIC VALUE PER SHARE (₹) | C45: =C42/C44 -> 895.19094
B46: Current Market Price (₹) | C46: ='🔑 Assumptions'!C93 -> 1165
B47: Upside / (Downside) % | C47: =(C45/C46-1) -> -0.23159576
B48: Verdict | C48: =IF(C47>0.1,"🟢 UNDERVALUED",IF(C47<-0.1,"🔴 OVERVALUED","🟡 FAIRLY VALUED")) -> 🔴 OVERVALUED

Sheet 🔬 Sensitivity
B1: SENSITIVITY ANALYSIS — IT SERVICES | Intrinsic Value Per Share (₹)
B2: Terminal Growth rate(col) | C2: ='🔑 Assumptions'!C14 -> 0.055 | E2: Wacc(row) | F2: ='🔑 Assumptions'!C75 -> 0.13726688
B3: TABLE — WACC (rows) vs Terminal Growth g (cols) | Auto-calculated | Green = IV > CMP
B4: ='💰 FCF & Val'!C45 -> 895.19094 | C4: 0.03 | D4: 0.04 | E4: 0.05 | F4: 0.055 | G4: 0.06 | H4: 0.065 | I4: 0.07
B5: 0.095 | C5: =( SUMPRODUCT('💰 FCF & Val'!$D$11:$K$11,1/(1+$B5)^('💰 FCF & Val'!$D$16:$K$16)) + ('💰 FCF & Val'!$K$11*(1+C$4)/($B5+('🔑 Assumptions'!$C$76-'🔑 Assumptions'!$C$75)-C$4))/(1+$B5)^8 + '💰 FCF & Val'!$C$40+'💰 FCF & Val'!$C$41-'💰 FCF & Val'!$C$38-'💰 FCF & Val'!$C$39 )/'💰 FCF & Val'!$C$44 -> 1233.355 | D5: =( SUMPRODUCT('💰 FCF & Val'!$D$11:$K$11,1/(1+$B5)^('💰 FCF & Val'!$D$16:$K$16)) + ('💰 FCF & Val'!$K$11*(1+D$4)/($B5+('🔑 Assumptions'!$C$76-'🔑 Assumptions'!$C$75)-D$4))/(1+$B5)^8 + '💰 FCF & Val'!$C$40+'💰 FCF & Val'!$C$41-'💰 FCF & Val'!$C$38-'💰 FCF & Val'!$C$39 )/'💰 FCF & Val'!$C$44 -> 1355.7469 | E5: =( SUMPRODUCT('💰 FCF & Val'!$D$11:$K$11,1/(1+$B5)^('💰 FCF & Val'!$D$16:$K$16)) + ('💰 FCF & Val'!$K$11*(1+E$4)/($B5+('🔑 Assumptions'!$C$76-'🔑 Assumptions'!$C$75)-E$4))/(1+$B5)^8 + '💰 FCF & Val'!$C$40+'💰 FCF & Val'!$C$41-'💰 FCF & Val'!$C$38-'💰 FCF & Val'!$C$39 )/'💰 FCF & Val'!$C$44 -> 1526.3125 | F5: =( SUMPRODUCT('💰 FCF & Val'!$D$11:$K$11,1/(1+$B5)^('💰 FCF & Val'!$D$16:$K$16)) + ('💰 FCF & Val'!$K$11*(1+F$4)/($B5+('🔑 Assumptions'!$C$76-'🔑 Assumptions'!$C$75)-F$4))/(1+$B5)^8 + '💰 FCF & Val'!$C$40+'💰 FCF & Val'!$C$41-'💰 FCF & Val'!$C$38-'💰 FCF & Val'!$C$39 )/'💰 FCF & Val'!$C$44 -> 1639.5185 | G5: =( SUMPRODUCT('💰 FCF & Val'!$D$11:$K$11,1/(1+$B5)^('💰 FCF & Val'!$D$16:$K$16)) + ('💰 FCF & Val'!$K$11*(1+G$4)/($B5+('🔑 Assumptions'!$C$76-'🔑 Assumptions'!$C$75)-G$4))/(1+$B5)^8 + '💰 FCF & Val'!$C$40+'💰 FCF & Val'!$C$41-'💰 FCF & Val'!$C$38-'💰 FCF & Val'!$C$39 )/'💰 FCF & Val'!$C$44 -> 1780.4625 | H5: =( SUMPRODUCT('💰 FCF & Val'!$D$11:$K$11,1/(1+$B5)^('💰 FCF & Val'!$D$16:$K$16)) + ('💰 FCF & Val'!$K$11*(1+H$4)/($B5+('🔑 Assumptions'!$C$76-'🔑 Assumptions'!$C$75)-H$4))/(1+$B5)^8 + '💰 FCF & Val'!$C$40+'💰 FCF & Val'!$C$41-'💰 FCF & Val'!$C$38-'💰 FCF & Val'!$C$39 )/'💰 FCF & Val'!$C$44 -> 1960.7622 | I5: =( SUMPRODUCT('💰 FCF & Val'!$D$11:$K$11,1/(1+$B5)^('💰 FCF & Val'!$D$16:$K$16)) + ('💰 FCF & Val'!$K$11*(1+I$4)/($B5+('🔑 Assumptions'!$C$76-'🔑 Assumptions'!$C$75)-I$4))/(1+$B5)^8 + '💰 FCF & Val'!$C$40+'💰 FCF & Val'!$C$41-'💰 FCF & Val'!$C$38-'💰 FCF & Val'!$C$39 )/'💰 FCF & Val'!$C$44 -> 2199.5766
B6: 0.1 | C6: =( SUMPRODUCT('💰 FCF & Val'!$D$11:$K$11,1/(1+$B6)^('💰 FCF & Val'!$D$16:$K$16)) + ('💰 FCF & Val'!$K$11*(1+C$4)/($B6+('🔑 Assumptions'!$C$76-'🔑 Assumptions'!$C$75)-C$4))/(1+$B6)^8 + '💰 FCF & Val'!$C$40+'💰 FCF & Val'!$C$41-'💰 FCF & Val'!$C$38-'💰 FCF & Val'!$C$39 )/'💰 FCF & Val'!$C$44 -> 1155.5543 | D6: =( SUMPRODUCT('💰 FCF & Val'!$D$11:$K$11,1/(1+$B6)^('💰 FCF & Val'!$D$16:$K$16)) + ('💰 FCF & Val'!$K$11*(1+D$4)/($B6+('🔑 Assumptions'!$C$76-'🔑 Assumptions'!$C$75)-D$4))/(1+$B6)^8 + '💰 FCF & Val'!$C$40+'💰 FCF & Val'!$C$41-'💰 FCF & Val'!$C$38-'💰 FCF & Val'!$C$39 )/'💰 FCF & Val'!$C$44 -> 1257.8709 | E6: =( SUMPRODUCT('💰 FCF & Val'!$D$11:$K$11,1/(1+$B6)^('💰 FCF & Val'!$D$16:$K$16)) + ('💰 FCF & Val'!$K$11*(1+E$4)/($B6+('🔑 Assumptions'!$C$76-'🔑 Assumptions'!$C$75)-E$4))/(1+$B6)^8 + '💰 FCF & Val'!$C$40+'💰 FCF & Val'!$C$41-'💰 FCF & Val'!$C$38-'💰 FCF & Val'!$C$39 )/'💰 FCF & Val'!$C$44 -> 1396.8517 | F6: =( SUMPRODUCT('💰 FCF & Val'!$D$11:$K$11,1/(1+$B6)^('💰 FCF & Val'!$D$16:$K$16)) + ('💰 FCF & Val'!$K$11*(1+F$4)/($B6+('🔑 Assumptions'!$C$76-'🔑 Assumptions'!$C$75)-F$4))/(1+$B6)^8 + '💰 FCF & Val'!$C$40+'💰 FCF & Val'!$C$41-'💰 FCF & Val'!$C$38-'💰 FCF & Val'!$C$39 )/'💰 FCF & Val'!$C$44 -> 1486.8558 | G6: =( SUMPRODUCT('💰 FCF & Val'!$D$11:$K$11,1/(1+$B6)^('💰 FCF & Val'!$D$16:$K$16)) + ('💰 FCF & Val'!$K$11*(1+G$4)/($B6+('🔑 Assumptions'!$C$76-'🔑 Assumptions'!$C$75)-G$4))/(1+$B6)^8 + '💰 FCF & Val'!$C$40+'💰 FCF & Val'!$C$41-'💰 FCF & Val'!$C$38-'💰 FCF & Val'!$C$39 )/'💰 FCF & Val'!$C$44 -> 1596.5059 | H6: =( SUMPRODUCT('💰 FCF & Val'!$D$11:$K$11,1/(1+$B6)^('💰 FCF & Val'!$D$16:$K$16)) + ('💰 FCF & Val'!$K$11*(1+H$4)/($B6+('🔑 Assumptions'!$C$76-'🔑 Assumptions'!$C$75)-H$4))/(1+$B6)^8 + '💰 FCF & Val'!$C$40+'💰 FCF & Val'!$C$41-'💰 FCF & Val'!$C$38-'💰 FCF & Val'!$C$39 )/'💰 FCF & Val'!$C$44 -> 1733.0227 | I6: =( SUMPRODUCT('💰 FCF & Val'!$D$11:$K$11,1/(1+$B6)^('💰 FCF & Val'!$D$16:$K$16)) + ('💰 FCF & Val'!$K$11*(1+I$4)/($B6+('🔑 Assumptions'!$C$76-'🔑 Assumptions'!$C$75)-I$4))/(1+$B6)^8 + '💰 FCF & Val'!$C$40+'💰 FCF & Val'!$C$41-'💰 FCF & Val'!$C$38-'💰 FCF & Val'!$C$39 )/'💰 FCF & Val'!$C$44 -> 1907.6591
B7: 0.11 | C7: =( SUMPRODUCT('💰 FCF & Val'!$D$11:$K$11,1/(1+$B7)^('💰 FCF & Val'!$D$16:$K$16)) + ('💰 FCF & Val'!$K$11*(1+C$4)/($B7+('🔑 Assumptions'!$C$76-'🔑 Assumptions'!$C$75)-C$4))/(1+$B7)^8 + '💰 FCF & Val'!$C$40+'💰 FCF & Val'!$C$41-'💰 FCF & Val'!$C$38-'💰 FCF & Val'!$C$39 )/'💰 FCF & Val'!$C$44 -> 1027.3254 | D7: =( SUMPRODUCT('💰 FCF & Val'!$D$11:$K$11,1/(1+$B7)^('💰 FCF & Val'!$D$16:$K$16)) + ('💰 FCF & Val'!$K$11*(1+D$4)/($B7+('🔑 Assumptions'!$C$76-'🔑 Assumptions'!$C$75)-D$4))/(1+$B7)^8 + '💰 FCF & Val'!$C$40+'💰 FCF & Val'!$C$41-'💰 FCF & Val'!$C$38-'💰 FCF & Val'!$C$39 )/'💰 FCF & Val'!$C$44 -> 1100.9752 | E7: =( SUMPRODUCT('💰 FCF & Val'!$D$11:$K$11,1/(1+$B7)^('💰 FCF & Val'!$D$16:$K$16)) + ('💰 FCF & Val'!$K$11*(1+E$4)/($B7+('🔑 Assumptions'!$C$76-'🔑 Assumptions'!$C$75)-E$4))/(1+$B7)^8 + '💰 FCF & Val'!$C$40+'💰 FCF & Val'!$C$41-'💰 FCF & Val'!$C$38-'💰 FCF & Val'!$C$39 )/'💰 FCF & Val'!$C$44 -> 1197.0066 | F7: =( SUMPRODUCT('💰 FCF & Val'!$D$11:$K$11,1/(1+$B7)^('💰 FCF & Val'!$D$16:$K$16)) + ('💰 FCF & Val'!$K$11*(1+F$4)/($B7+('🔑 Assumptions'!$C$76-'🔑 Assumptions'!$C$75)-F$4))/(1+$B7)^8 + '💰 FCF & Val'!$C$40+'💰 FCF & Val'!$C$41-'💰 FCF & Val'!$C$38-'💰 FCF & Val'!$C$39 )/'💰 FCF & Val'!$C$44 -> 1256.8658 | G7: =( SUMPRODUCT('💰 FCF & Val'!$D$11:$K$11,1/(1+$B7)^('💰 FCF & Val'!$D$16:$K$16)) + ('💰 FCF & Val'!$K$11*(1+G$4)/($B7+('🔑 Assumptions'!$C$76-'🔑 Assumptions'!$C$75)-G$4))/(1+$B7)^8 + '💰 FCF & Val'!$C$40+'💰 FCF & Val'!$C$41-'💰 FCF & Val'!$C$38-'💰 FCF & Val'!$C$39 )/'💰 FCF & Val'!$C$44 -> 1327.4501 | H7: =( SUMPRODUCT('💰 FCF & Val'!$D$11:$K$11,1/(1+$B7)^('💰 FCF & Val'!$D$16:$K$16)) + ('💰 FCF & Val'!$K$11*(1+H$4)/($B7+('🔑 Assumptions'!$C$76-'🔑 Assumptions'!$C$75)-H$4))/(1+$B7)^8 + '💰 FCF & Val'!$C$40+'💰 FCF & Val'!$C$41-'💰 FCF & Val'!$C$38-'💰 FCF & Val'!$C$39 )/'💰 FCF & Val'!$C$44 -> 1411.9253 | I7: =( SUMPRODUCT('💰 FCF & Val'!$D$11:$K$11,1/(1+$B7)^('💰 FCF & Val'!$D$16:$K$16)) + ('💰 FCF & Val'!$K$11*(1+I$4)/($B7+('🔑 Assumptions'!$C$76-'🔑 Assumptions'!$C$75)-I$4))/(1+$B7)^8 + '💰 FCF & Val'!$C$40+'💰 FCF & Val'!$C$41-'💰 FCF & Val'!$C$38-'💰 FCF & Val'!$C$39 )/'💰 FCF & Val'!$C$44 -> 1514.8398
B8: 0.12 | C8: =( SUMPRODUCT('💰 FCF & Val'!$D$11:$K$11,1/(1+$B8)^('💰 FCF & Val'!$D$16:$K$16)) + ('💰 FCF & Val'!$K$11*(1+C$4)/($B8+('🔑 Assumptions'!$C$76-'🔑 Assumptions'!$C$75)-C$4))/(1+$B8)^8 + '💰 FCF & Val'!$C$40+'💰 FCF & Val'!$C$41-'💰 FCF & Val'!$C$38-'💰 FCF & Val'!$C$39 )/'💰 FCF & Val'!$C$44 -> 926.0589 | D8: =( SUMPRODUCT('💰 FCF & Val'!$D$11:$K$11,1/(1+$B8)^('💰 FCF & Val'!$D$16:$K$16)) + ('💰 FCF & Val'!$K$11*(1+D$4)/($B8+('🔑 Assumptions'!$C$76-'🔑 Assumptions'!$C$75)-D$4))/(1+$B8)^8 + '💰 FCF & Val'!$C$40+'💰 FCF & Val'!$C$41-'💰 FCF & Val'!$C$38-'💰 FCF & Val'!$C$39 )/'💰 FCF & Val'!$C$44 -> 980.78634 | E8: =( SUMPRODUCT('💰 FCF & Val'!$D$11:$K$11,1/(1+$B8)^('💰 FCF & Val'!$D$16:$K$16)) + ('💰 FCF & Val'!$K$11*(1+E$4)/($B8+('🔑 Assumptions'!$C$76-'🔑 Assumptions'!$C$75)-E$4))/(1+$B8)^8 + '💰 FCF & Val'!$C$40+'💰 FCF & Val'!$C$41-'💰 FCF & Val'!$C$38-'💰 FCF & Val'!$C$39 )/'💰 FCF & Val'!$C$44 -> 1049.9513 | F8: =( SUMPRODUCT('💰 FCF & Val'!$D$11:$K$11,1/(1+$B8)^('💰 FCF & Val'!$D$16:$K$16)) + ('💰 FCF & Val'!$K$11*(1+F$4)/($B8+('🔑 Assumptions'!$C$76-'🔑 Assumptions'!$C$75)-F$4))/(1+$B8)^8 + '💰 FCF & Val'!$C$40+'💰 FCF & Val'!$C$41-'💰 FCF & Val'!$C$38-'💰 FCF & Val'!$C$39 )/'💰 FCF & Val'!$C$44 -> 1091.8593 | G8: =( SUMPRODUCT('💰 FCF & Val'!$D$11:$K$11,1/(1+$B8)^('💰 FCF & Val'!$D$16:$K$16)) + ('💰 FCF & Val'!$K$11*(1+G$4)/($B8+('🔑 Assumptions'!$C$76-'🔑 Assumptions'!$C$75)-G$4))/(1+$B8)^8 + '💰 FCF & Val'!$C$40+'💰 FCF & Val'!$C$41-'💰 FCF & Val'!$C$38-'💰 FCF & Val'!$C$39 )/'💰 FCF & Val'!$C$44 -> 1140.135 | H8: =( SUMPRODUCT('💰 FCF & Val'!$D$11:$K$11,1/(1+$B8)^('💰 FCF & Val'!$D$16:$K$16)) + ('💰 FCF & Val'!$K$11*(1+H$4)/($B8+('🔑 Assumptions'!$C$76-'🔑 Assumptions'!$C$75)-H$4))/(1+$B8)^8 + '💰 FCF & Val'!$C$40+'💰 FCF & Val'!$C$41-'💰 FCF & Val'!$C$38-'💰 FCF & Val'!$C$39 )/'💰 FCF & Val'!$C$44 -> 1196.3491 | I8: =( SUMPRODUCT('💰 FCF & Val'!$D$11:$K$11,1/(1+$B8)^('💰 FCF & Val'!$D$16:$K$16)) + ('💰 FCF & Val'!$K$11*(1+I$4)/($B8+('🔑 Assumptions'!$C$76-'🔑 Assumptions'!$C$75)-I$4))/(1+$B8)^8 + '💰 FCF & Val'!$C$40+'💰 FCF & Val'!$C$41-'💰 FCF & Val'!$C$38-'💰 FCF & Val'!$C$39 )/'💰 FCF & Val'!$C$44 -> 1262.6351
B9: 0.125 | C9: =( SUMPRODUCT('💰 FCF & Val'!$D$11:$K$11,1/(1+$B9)^('💰 FCF & Val'!$D$16:$K$16)) + ('💰 FCF & Val'!$K$11*(1+C$4)/($B9+('🔑 Assumptions'!$C$76-'🔑 Assumptions'!$C$75)-C$4))/(1+$B9)^8 + '💰 FCF & Val'!$C$40+'💰 FCF & Val'!$C$41-'💰 FCF & Val'!$C$38-'💰 FCF & Val'!$C$39 )/'💰 FCF & Val'!$C$44 -> 883.02545 | D9: =( SUMPRODUCT('💰 FCF & Val'!$D$11:$K$11,1/(1+$B9)^('💰 FCF & Val'!$D$16:$K$16)) + ('💰 FCF & Val'!$K$11*(1+D$4)/($B9+('🔑 Assumptions'!$C$76-'🔑 Assumptions'!$C$75)-D$4))/(1+$B9)^8 + '💰 FCF & Val'!$C$40+'💰 FCF & Val'!$C$41-'💰 FCF & Val'!$C$38-'💰 FCF & Val'!$C$39 )/'💰 FCF & Val'!$C$44 -> 930.66487 | E9: =( SUMPRODUCT('💰 FCF & Val'!$D$11:$K$11,1/(1+$B9)^('💰 FCF & Val'!$D$16:$K$16)) + ('💰 FCF & Val'!$K$11*(1+E$4)/($B9+('🔑 Assumptions'!$C$76-'🔑 Assumptions'!$C$75)-E$4))/(1+$B9)^8 + '💰 FCF & Val'!$C$40+'💰 FCF & Val'!$C$41-'💰 FCF & Val'!$C$38-'💰 FCF & Val'!$C$39 )/'💰 FCF & Val'!$C$44 -> 990.09436 | F9: =( SUMPRODUCT('💰 FCF & Val'!$D$11:$K$11,1/(1+$B9)^('💰 FCF & Val'!$D$16:$K$16)) + ('💰 FCF & Val'!$K$11*(1+F$4)/($B9+('🔑 Assumptions'!$C$76-'🔑 Assumptions'!$C$75)-F$4))/(1+$B9)^8 + '💰 FCF & Val'!$C$40+'💰 FCF & Val'!$C$41-'💰 FCF & Val'!$C$38-'💰 FCF & Val'!$C$39 )/'💰 FCF & Val'!$C$44 -> 1025.6883 | G9: =( SUMPRODUCT('💰 FCF & Val'!$D$11:$K$11,1/(1+$B9)^('💰 FCF & Val'!$D$16:$K$16)) + ('💰 FCF & Val'!$K$11*(1+G$4)/($B9+('🔑 Assumptions'!$C$76-'🔑 Assumptions'!$C$75)-G$4))/(1+$B9)^8 + '💰 FCF & Val'!$C$40+'💰 FCF & Val'!$C$41-'💰 FCF & Val'!$C$38-'💰 FCF & Val'!$C$39 )/'💰 FCF & Val'!$C$44 -> 1066.3088 | H9: =( SUMPRODUCT('💰 FCF & Val'!$D$11:$K$11,1/(1+$B9)^('💰 FCF & Val'!$D$16:$K$16)) + ('💰 FCF & Val'!$K$11*(1+H$4)/($B9+('🔑 Assumptions'!$C$76-'🔑 Assumptions'!$C$75)-H$4))/(1+$B9)^8 + '💰 FCF & Val'!$C$40+'💰 FCF & Val'!$C$41-'💰 FCF & Val'!$C$38-'💰 FCF & Val'!$C$39 )/'💰 FCF & Val'!$C$44 -> 1113.1014 | I9: =( SUMPRODUCT('💰 FCF & Val'!$D$11:$K$11,1/(1+$B9)^('💰 FCF & Val'!$D$16:$K$16)) + ('💰 FCF & Val'!$K$11*(1+I$4)/($B9+('🔑 Assumptions'!$C$76-'🔑 Assumptions'!$C$75)-I$4))/(1+$B9)^8 + '💰 FCF & Val'!$C$40+'💰 FCF & Val'!$C$41-'💰 FCF & Val'!$C$38-'💰 FCF & Val'!$C$39 )/'💰 FCF & Val'!$C$44 -> 1167.5886
B10: 0.13 | C10: =( SUMPRODUCT('💰 FCF & Val'!$D$11:$K$11,1/(1+$B10)^('💰 FCF & Val'!$D$16:$K$16)) + ('💰 FCF & Val'!$K$11*(1+C$4)/($B10+('🔑 Assumptions'!$C$76-'🔑 Assumptions'!$C$75)-C$4))/(1+$B10)^8 + '💰 FCF & Val'!$C$40+'💰 FCF & Val'!$C$41-'💰 FCF & Val'!$C$38-'💰 FCF & Val'!$C$39 )/'💰 FCF & Val'!$C$44 -> 844.09907 | D10: =( SUMPRODUCT('💰 FCF & Val'!$D$11:$K$11,1/(1+$B10)^('💰 FCF & Val'!$D$16:$K$16)) + ('💰 FCF & Val'!$K$11*(1+D$4)/($B10+('🔑 Assumptions'!$C$76-'🔑 Assumptions'!$C$75)-D$4))/(1+$B10)^8 + '💰 FCF & Val'!$C$40+'💰 FCF & Val'!$C$41-'💰 FCF & Val'!$C$38-'💰 FCF & Val'!$C$39 )/'💰 FCF & Val'!$C$44 -> 885.80291 | E10: =( SUMPRODUCT('💰 FCF & Val'!$D$11:$K$11,1/(1+$B10)^('💰 FCF & Val'!$D$16:$K$16)) + ('💰 FCF & Val'!$K$11*(1+E$4)/($B10+('🔑 Assumptions'!$C$76-'🔑 Assumptions'!$C$75)-E$4))/(1+$B10)^8 + '💰 FCF & Val'!$C$40+'💰 FCF & Val'!$C$41-'💰 FCF & Val'!$C$38-'💰 FCF & Val'!$C$39 )/'💰 FCF & Val'!$C$44 -> 937.22649 | F10: =( SUMPRODUCT('💰 FCF & Val'!$D$11:$K$11,1/(1+$B10)^('💰 FCF & Val'!$D$16:$K$16)) + ('💰 FCF & Val'!$K$11*(1+F$4)/($B10+('🔑 Assumptions'!$C$76-'🔑 Assumptions'!$C$75)-F$4))/(1+$B10)^8 + '💰 FCF & Val'!$C$40+'💰 FCF & Val'!$C$41-'💰 FCF & Val'!$C$38-'💰 FCF & Val'!$C$39 )/'💰 FCF & Val'!$C$44 -> 967.71075 | G10: =( SUMPRODUCT('💰 FCF & Val'!$D$11:$K$11,1/(1+$B10)^('💰 FCF & Val'!$D$16:$K$16)) + ('💰 FCF & Val'!$K$11*(1+G$4)/($B10+('🔑 Assumptions'!$C$76-'🔑 Assumptions'!$C$75)-G$4))/(1+$B10)^8 + '💰 FCF & Val'!$C$40+'💰 FCF & Val'!$C$41-'💰 FCF & Val'!$C$38-'💰 FCF & Val'!$C$39 )/'💰 FCF & Val'!$C$44 -> 1002.216 | H10: =( SUMPRODUCT('💰 FCF & Val'!$D$11:$K$11,1/(1+$B10)^('💰 FCF & Val'!$D$16:$K$16)) + ('💰 FCF & Val'!$K$11*(1+H$4)/($B10+('🔑 Assumptions'!$C$76-'🔑 Assumptions'!$C$75)-H$4))/(1+$B10)^8 + '💰 FCF & Val'!$C$40+'💰 FCF & Val'!$C$41-'💰 FCF & Val'!$C$38-'💰 FCF & Val'!$C$39 )/'💰 FCF & Val'!$C$44 -> 1041.594 | I10: =( SUMPRODUCT('💰 FCF & Val'!$D$11:$K$11,1/(1+$B10)^('💰 FCF & Val'!$D$16:$K$16)) + ('💰 FCF & Val'!$K$11*(1+I$4)/($B10+('🔑 Assumptions'!$C$76-'🔑 Assumptions'!$C$75)-I$4))/(1+$B10)^8 + '💰 FCF & Val'!$C$40+'💰 FCF & Val'!$C$41-'💰 FCF & Val'!$C$38-'💰 FCF & Val'!$C$39 )/'💰 FCF & Val'!$C$44 -> 1086.9554
B11: 0.14 | C11: =( SUMPRODUCT('💰 FCF & Val'!$D$11:$K$11,1/(1+$B11)^('💰 FCF & Val'!$D$16:$K$16)) + ('💰 FCF & Val'!$K$11*(1+C$4)/($B11+('🔑 Assumptions'!$C$76-'🔑 Assumptions'!$C$75)-C$4))/(1+$B11)^8 + '💰 FCF & Val'!$C$40+'💰 FCF & Val'!$C$41-'💰 FCF & Val'!$C$38-'💰 FCF & Val'!$C$39 )/'💰 FCF & Val'!$C$44 -> 776.43505 | D11: =( SUMPRODUCT('💰 FCF & Val'!$D$11:$K$11,1/(1+$B11)^('💰 FCF & Val'!$D$16:$K$16)) + ('💰 FCF & Val'!$K$11*(1+D$4)/($B11+('🔑 Assumptions'!$C$76-'🔑 Assumptions'!$C$75)-D$4))/(1+$B11)^8 + '💰 FCF & Val'!$C$40+'💰 FCF & Val'!$C$41-'💰 FCF & Val'!$C$38-'💰 FCF & Val'!$C$39 )/'💰 FCF & Val'!$C$44 -> 808.8719 | E11: =( SUMPRODUCT('💰 FCF & Val'!$D$11:$K$11,1/(1+$B11)^('💰 FCF & Val'!$D$16:$K$16)) + ('💰 FCF & Val'!$K$11*(1+E$4)/($B11+('🔑 Assumptions'!$C$76-'🔑 Assumptions'!$C$75)-E$4))/(1+$B11)^8 + '💰 FCF & Val'!$C$40+'💰 FCF & Val'!$C$41-'💰 FCF & Val'!$C$38-'💰 FCF & Val'!$C$39 )/'💰 FCF & Val'!$C$44 -> 848.07964 | F11: =( SUMPRODUCT('💰 FCF & Val'!$D$11:$K$11,1/(1+$B11)^('💰 FCF & Val'!$D$16:$K$16)) + ('💰 FCF & Val'!$K$11*(1+F$4)/($B11+('🔑 Assumptions'!$C$76-'🔑 Assumptions'!$C$75)-F$4))/(1+$B11)^8 + '💰 FCF & Val'!$C$40+'💰 FCF & Val'!$C$41-'💰 FCF & Val'!$C$38-'💰 FCF & Val'!$C$39 )/'💰 FCF & Val'!$C$44 -> 870.92157 | G11: =( SUMPRODUCT('💰 FCF & Val'!$D$11:$K$11,1/(1+$B11)^('💰 FCF & Val'!$D$16:$K$16)) + ('💰 FCF & Val'!$K$11*(1+G$4)/($B11+('🔑 Assumptions'!$C$76-'🔑 Assumptions'!$C$75)-G$4))/(1+$B11)^8 + '💰 FCF & Val'!$C$40+'💰 FCF & Val'!$C$41-'💰 FCF & Val'!$C$38-'💰 FCF & Val'!$C$39 )/'💰 FCF & Val'!$C$44 -> 896.42535 | H11: =( SUMPRODUCT('💰 FCF & Val'!$D$11:$K$11,1/(1+$B11)^('💰 FCF & Val'!$D$16:$K$16)) + ('💰 FCF & Val'!$K$11*(1+H$4)/($B11+('🔑 Assumptions'!$C$76-'🔑 Assumptions'!$C$75)-H$4))/(1+$B11)^8 + '💰 FCF & Val'!$C$40+'💰 FCF & Val'!$C$41-'💰 FCF & Val'!$C$38-'💰 FCF & Val'!$C$39 )/'💰 FCF & Val'!$C$44 -> 925.08503 | I11: =( SUMPRODUCT('💰 FCF & Val'!$D$11:$K$11,1/(1+$B11)^('💰 FCF & Val'!$D$16:$K$16)) + ('💰 FCF & Val'!$K$11*(1+I$4)/($B11+('🔑 Assumptions'!$C$76-'🔑 Assumptions'!$C$75)-I$4))/(1+$B11)^8 + '💰 FCF & Val'!$C$40+'💰 FCF & Val'!$C$41-'💰 FCF & Val'!$C$38-'💰 FCF & Val'!$C$39 )/'💰 FCF & Val'!$C$44 -> 957.52503
B12: 0.15 | C12: =( SUMPRODUCT('💰 FCF & Val'!$D$11:$K$11,1/(1+$B12)^('💰 FCF & Val'!$D$16:$K$16)) + ('💰 FCF & Val'!$K$11*(1+C$4)/($B12+('🔑 Assumptions'!$C$76-'🔑 Assumptions'!$C$75)-C$4))/(1+$B12)^8 + '💰 FCF & Val'!$C$40+'💰 FCF & Val'!$C$41-'💰 FCF & Val'!$C$38-'💰 FCF & Val'!$C$39 )/'💰 FCF & Val'!$C$44 -> 719.6498 | D12: =( SUMPRODUCT('💰 FCF & Val'!$D$11:$K$11,1/(1+$B12)^('💰 FCF & Val'!$D$16:$K$16)) + ('💰 FCF & Val'!$K$11*(1+D$4)/($B12+('🔑 Assumptions'!$C$76-'🔑 Assumptions'!$C$75)-D$4))/(1+$B12)^8 + '💰 FCF & Val'!$C$40+'💰 FCF & Val'!$C$41-'💰 FCF & Val'!$C$38-'💰 FCF & Val'!$C$39 )/'💰 FCF & Val'!$C$44 -> 745.3113 | E12: =( SUMPRODUCT('💰 FCF & Val'!$D$11:$K$11,1/(1+$B12)^('💰 FCF & Val'!$D$16:$K$16)) + ('💰 FCF & Val'!$K$11*(1+E$4)/($B12+('🔑 Assumptions'!$C$76-'🔑 Assumptions'!$C$75)-E$4))/(1+$B12)^8 + '💰 FCF & Val'!$C$40+'💰 FCF & Val'!$C$41-'💰 FCF & Val'!$C$38-'💰 FCF & Val'!$C$39 )/'💰 FCF & Val'!$C$44 -> 775.82315 | F12: =( SUMPRODUCT('💰 FCF & Val'!$D$11:$K$11,1/(1+$B12)^('💰 FCF & Val'!$D$16:$K$16)) + ('💰 FCF & Val'!$K$11*(1+F$4)/($B12+('🔑 Assumptions'!$C$76-'🔑 Assumptions'!$C$75)-F$4))/(1+$B12)^8 + '💰 FCF & Val'!$C$40+'💰 FCF & Val'!$C$41-'💰 FCF & Val'!$C$38-'💰 FCF & Val'!$C$39 )/'💰 FCF & Val'!$C$44 -> 793.34902 | G12: =( SUMPRODUCT('💰 FCF & Val'!$D$11:$K$11,1/(1+$B12)^('💰 FCF & Val'!$D$16:$K$16)) + ('💰 FCF & Val'!$K$11*(1+G$4)/($B12+('🔑 Assumptions'!$C$76-'🔑 Assumptions'!$C$75)-G$4))/(1+$B12)^8 + '💰 FCF & Val'!$C$40+'💰 FCF & Val'!$C$41-'💰 FCF & Val'!$C$38-'💰 FCF & Val'!$C$39 )/'💰 FCF & Val'!$C$44 -> 812.70407 | H12: =( SUMPRODUCT('💰 FCF & Val'!$D$11:$K$11,1/(1+$B12)^('💰 FCF & Val'!$D$16:$K$16)) + ('💰 FCF & Val'!$K$11*(1+H$4)/($B12+('🔑 Assumptions'!$C$76-'🔑 Assumptions'!$C$75)-H$4))/(1+$B12)^8 + '💰 FCF & Val'!$C$40+'💰 FCF & Val'!$C$41-'💰 FCF & Val'!$C$38-'💰 FCF & Val'!$C$39 )/'💰 FCF & Val'!$C$44 -> 834.19043 | I12: =( SUMPRODUCT('💰 FCF & Val'!$D$11:$K$11,1/(1+$B12)^('💰 FCF & Val'!$D$16:$K$16)) + ('💰 FCF & Val'!$K$11*(1+I$4)/($B12+('🔑 Assumptions'!$C$76-'🔑 Assumptions'!$C$75)-I$4))/(1+$B12)^8 + '💰 FCF & Val'!$C$40+'💰 FCF & Val'!$C$41-'💰 FCF & Val'!$C$38-'💰 FCF & Val'!$C$39 )/'💰 FCF & Val'!$C$44 -> 858.18065
B13: IT SECTOR WACC BENCHMARKS: Large-cap (TCS/Infy): 11–13% | Mid-cap IT: 13–15% | Small-cap IT: 15–17%
B14: TERMINAL GROWTH BENCHMARKS: Conservative: 5.0% | Base: 5.5% | Bullish: 6.0% | Note: India nominal GDP growth ~6.5-7%
B15: These cells now auto-populate via direct formulas (no Excel Data Table needed). Each cell re-discounts the fixed FCFF stream at its row WACC and rebuilds the terminal value at its (WACC, g). Green = intrinsic value above current market price.

Sheet 📐 Beta Calc
B1: BETA CALCULATION — 3-Year Weekly Price Data | IT Sector
B4: BETA OUTPUT
B5: Metric | C5: Value | G5: Note
B6: Calculated Beta (Raw) | C6: =SLOPE(F17:F172,E17:E172) -> 0.91809063 | G6: SLOPE(stock weekly returns, Nifty50 weekly returns). IT large-cap benchmarks: TCS ~0.7, Infosys ~0.8, HCL ~0.9, Wipro ~0.9, Tech M ~1.0. If Beta > 1.2 for large-cap IT, check your data.
B7: Beta Used in Model | C7: =B6 -> Calculated Beta (Raw) | G7: This cell links to Assumptions Section F. Verify before finalising.
B8: Data Points (weeks) | C8: =COUNTA(B16:B172) -> 157 | G8: Should be ~156 (3Y × 52W). Less = incomplete data.
B9: R-squared | C9: =IFERROR(RSQ(F17:F172,E17:E172),0) -> 0.17928749 | G9: R² > 0.3 typical for liquid large-caps.
B13: 📌 Steps: (1) Trendlyne.com → Company → Charts → Download weekly prices (3Y) → paste Closing Price → Col C OR investing.com → Nifty 50 → Historical → Weekly → 3 years → Download → paste Price col → Col C | (2) Same for your IT stock → Col D | (3) Same date range, same row count, oldest date at TOP | ⚠ IT stocks: expect Beta 0.6–1.0 for large-cap, 0.8–1.2 for mid-cap
B14: Date | C14: Nifty50 Price | D14: Stock Price | E14: Nifty50 Weekly Ret | F14: Stock Weekly Return
B15: 📌 Steps: (1) Trendlyne.com → Company → Charts → Download weekly prices (3Y) → paste Closing Price → Col C OR investing.com → Nifty 50 → Historical → Weekly → 3 years → Download → paste Price col → Col C | (2) Same for your IT stock → Col D | (3) Same date range, same row count, oldest date at TOP | ⚠ IT stocks: expect Beta 0.6–1.0 for large-cap, 0.8–1.2 for mid-cap
B16: 05/24/2026 | C16: 24031.7 | D16: 1165.2 | E16: "-" | F16: "-"
B17: 05/17/2026 | C17: 23719.3 | D17: 1164 | E17: =C17/C16-1 -> -0.012999496 | F17: =D17/D16-1 -> -0.0010298661
B18: 46300 | C18: 23643.5 | D18: 1132.6 | E18: =C18/C17-1 -> -0.0031957098 | F18: =D18/D17-1 -> -0.026975945
B19: 46086 | C19: 24176.15 | D19: 1198.4 | E19: =C19/C18-1 -> 0.02252839 | F19: =D19/D18-1 -> 0.058096415
B20: 04/26/2026 | C20: 23997.55 | D20: 1199.1 | E20: =C20/C19-1 -> -0.0073874459 | F20: =D20/D19-1 -> 0.00058411215
B21: 04/19/2026 | C21: 23897.95 | D21: 1203.2 | E21: =C21/C20-1 -> -0.0041504237 | F21: =D21/D20-1 -> 0.0034192311
B22: 46360 | C22: 24353.55 | D22: 1442.3 | E22: =C22/C21-1 -> 0.019064397 | F22: =D22/D21-1 -> 0.19872008
B23: 46146 | C23: 24050.6 | D23: 1451.2 | E23: =C23/C22-1 -> -0.012439665 | F23: =D23/D22-1 -> 0.0061706996
B24: 03/29/2026 | C24: 22713.1 | D24: 1402.2 | E24: =C24/C23-1 -> -0.055611918 | F24: =D24/D23-1 -> -0.03376516
B25: 03/22/2026 | C25: 22819.6 | D25: 1364.4 | E25: =C25/C24-1 -> 0.004688924 | F25: =D25/D24-1 -> -0.026957638
B26: 03/15/2026 | C26: 23114.5 | D26: 1333.7 | E26: =C26/C25-1 -> 0.012923101 | F26: =D26/D25-1 -> -0.022500733
B27: 46237 | C27: 23151.1 | D27: 1325.4 | E27: =C27/C26-1 -> 0.0015834217 | F27: =D27/D26-1 -> -0.0062232886
B28: 46025 | C28: 24450.45 | D28: 1356.7 | E28: =C28/C27-1 -> 0.056124763 | F28: =D28/D27-1 -> 0.023615512
B29: 02/22/2026 | C29: 25178.65 | D29: 1389.1 | E29: =C29/C28-1 -> 0.029782683 | F29: =D29/D28-1 -> 0.023881477
B30: 02/15/2026 | C30: 25571.25 | D30: 1436.5 | E30: =C30/C29-1 -> 0.015592575 | F30: =D30/D29-1 -> 0.034122813
B31: 46236 | C31: 25471.1 | D31: 1455.2 | E31: =C31/C30-1 -> -0.0039165078 | F31: =D31/D30-1 -> 0.013017751
B32: 46024 | C32: 25693.7 | D32: 1593.7 | E32: =C32/C31-1 -> 0.0087393163 | F32: =D32/D31-1 -> 0.095175921
B33: 01/25/2026 | C33: 25320.65 | D33: 1695.6 | E33: =C33/C32-1 -> -0.014519123 | F33: =D33/D32-1 -> 0.063939261
B34: 01/18/2026 | C34: 25048.65 | D34: 1707 | E34: =C34/C33-1 -> -0.01074222 | F34: =D34/D33-1 -> 0.0067232838
B35: 46327 | C35: 25694.35 | D35: 1698 | E35: =C35/C34-1 -> 0.025777836 | F35: =D35/D34-1 -> -0.0052724077
B36: 46113 | C36: 25683.3 | D36: 1661.4 | E36: =C36/C35-1 -> -0.00043005563 | F36: =D36/D35-1 -> -0.02155477
B37: 12/28/2025 | C37: 26328.55 | D37: 1640.2 | E37: =C37/C36-1 -> 0.025123329 | F37: =D37/D36-1 -> -0.012760323
B38: 12/21/2025 | C38: 26042.3 | D38: 1660.9 | E38: =C38/C37-1 -> -0.010872228 | F38: =D38/D37-1 -> 0.012620412
B39: 12/14/2025 | C39: 25966.4 | D39: 1642.4 | E39: =C39/C38-1 -> -0.0029144891 | F39: =D39/D38-1 -> -0.011138539
B40: 45850 | C40: 26046.95 | D40: 1673.2 | E40: =C40/C39-1 -> 0.0031020858 | F40: =D40/D39-1 -> 0.018753044
B41: 11/30/2025 | C41: 26186.45 | D41: 1683 | E41: =C41/C40-1 -> 0.0053557134 | F41: =D41/D40-1 -> 0.0058570404
B42: 11/23/2025 | C42: 26202.95 | D42: 1624.2 | E42: =C42/C41-1 -> 0.00063009686 | F42: =D42/D41-1 -> -0.034937611
B43: 11/16/2025 | C43: 26068.15 | D43: 1608 | E43: =C43/C42-1 -> -0.0051444589 | F43: =D43/D42-1 -> -0.0099741411
B44: 45911 | C44: 25910.05 | D44: 1594.6 | E44: =C44/C43-1 -> -0.0060648723 | F44: =D44/D43-1 -> -0.0083333333
B45: 45699 | C45: 25492.3 | D45: 1512.4 | E45: =C45/C44-1 -> -0.016123087 | F45: =D45/D44-1 -> -0.051548978
B46: 10/26/2025 | C46: 25722.1 | D46: 1541.5 | E46: =C46/C45-1 -> 0.0090144867 | F46: =D46/D45-1 -> 0.019240942
B47: 10/19/2025 | C47: 25795.15 | D47: 1523.8 | E47: =C47/C46-1 -> 0.0028399703 | F47: =D47/D46-1 -> -0.011482322
B48: 46001 | C48: 25709.85 | D48: 1486.2 | E48: =C48/C47-1 -> -0.0033068232 | F48: =D48/D47-1 -> -0.024675154
B49: 45787 | C49: 25285.35 | D49: 1495.5 | E49: =C49/C48-1 -> -0.016511182 | F49: =D49/D48-1 -> 0.0062575696
B50: 09/28/2025 | C50: 24894.25 | D50: 1393.5 | E50: =C50/C49-1 -> -0.015467454 | F50: =D50/D49-1 -> -0.068204614
B51: 09/21/2025 | C51: 24654.7 | D51: 1395.3 | E51: =C51/C50-1 -> -0.009622704 | F51: =D51/D50-1 -> 0.0012917115
B52: 09/14/2025 | C52: 25327.05 | D52: 1467.4 | E52: =C52/C51-1 -> 0.027270662 | F52: =D52/D51-1 -> 0.051673475
B53: 45847 | C53: 25114 | D53: 1467.2 | E53: =C53/C52-1 -> -0.0084119548 | F53: =D53/D52-1 -> -0.00013629549
B54: 08/31/2025 | C54: 24741 | D54: 1419 | E54: =C54/C53-1 -> -0.014852274 | F54: =D54/D53-1 -> -0.03285169
B55: 08/24/2025 | C55: 24426.85 | D55: 1454.8 | E55: =C55/C54-1 -> -0.012697547 | F55: =D55/D54-1 -> 0.025229035
B56: 08/17/2025 | C56: 24870.1 | D56: 1466.3 | E56: =C56/C55-1 -> 0.018146016 | F56: =D56/D55-1 -> 0.0079048666
B57: 45938 | C57: 24631.3 | D57: 1489.8 | E57: =C57/C56-1 -> -0.0096018914 | F57: =D57/D56-1 -> 0.016026734
B58: 45724 | C58: 24363.3 | D58: 1475.7 | E58: =C58/C57-1 -> -0.010880465 | F58: =D58/D57-1 -> -0.0094643576
B59: 07/27/2025 | C59: 24565.35 | D59: 1452.1 | E59: =C59/C58-1 -> 0.0082932115 | F59: =D59/D58-1 -> -0.01599241
B60: 07/20/2025 | C60: 24837 | D60: 1490.1 | E60: =C60/C59-1 -> 0.011058259 | F60: =D60/D59-1 -> 0.026168997
B61: 07/13/2025 | C61: 24968.4 | D61: 1548.8 | E61: =C61/C60-1 -> 0.005290494 | F61: =D61/D60-1 -> 0.039393329
B62: 45815 | C62: 25149.85 | D62: 1638.3 | E62: =C62/C61-1 -> 0.0072671857 | F62: =D62/D61-1 -> 0.057786674
B63: 06/29/2025 | C63: 25461 | D63: 1725.9 | E63: =C63/C62-1 -> 0.012371843 | F63: =D63/D62-1 -> 0.05347006
B64: 06/22/2025 | C64: 25637.8 | D64: 1723.3 | E64: =C64/C63-1 -> 0.0069439535 | F64: =D64/D63-1 -> -0.0015064604
B65: 06/15/2025 | C65: 25112.4 | D65: 1739.9 | E65: =C65/C64-1 -> -0.020493178 | F65: =D65/D64-1 -> 0.0096326815
B66: 45875 | C66: 24718.6 | D66: 1695.3 | E66: =C66/C65-1 -> -0.015681496 | F66: =D66/D65-1 -> -0.025633657
B67: 45663 | C67: 25003.05 | D67: 1637.7 | E67: =C67/C66-1 -> 0.011507529 | F67: =D67/D66-1 -> -0.033976287
B68: 05/25/2025 | C68: 24750.7 | D68: 1636.6 | E68: =C68/C67-1 -> -0.010092769 | F68: =D68/D67-1 -> -0.00067167369
B69: 05/18/2025 | C69: 24853.15 | D69: 1648.2 | E69: =C69/C68-1 -> 0.0041392769 | F69: =D69/D68-1 -> 0.0070878651
B70: 45966 | C70: 25019.8 | D70: 1659.9 | E70: =C70/C69-1 -> 0.0067053874 | F70: =D70/D69-1 -> 0.0070986531
B71: 45752 | C71: 24008 | D71: 1569.4 | E71: =C71/C70-1 -> -0.040439972 | F71: =D71/D70-1 -> -0.054521357
B72: 04/27/2025 | C72: 24346.7 | D72: 1576.5 | E72: =C72/C71-1 -> 0.014107797 | F72: =D72/D71-1 -> 0.0045240219
B73: 04/20/2025 | C73: 24039.35 | D73: 1578.2 | E73: =C73/C72-1 -> -0.012623887 | F73: =D73/D72-1 -> 0.0010783381
B74: 04/13/2025 | C74: 23851.65 | D74: 1438 | E74: =C74/C73-1 -> -0.0078080314 | F74: =D74/D73-1 -> -0.088835382
B75: 45812 | C75: 22828.55 | D75: 1390.55 | E75: =C75/C74-1 -> -0.042894307 | F75: =D75/D74-1 -> -0.032997218
B76: 03/30/2025 | C76: 22904.45 | D76: 1422.1 | E76: =C76/C75-1 -> 0.0033247841 | F76: =D76/D75-1 -> 0.022688864
B77: 03/23/2025 | C77: 23519.35 | D77: 1592.5 | E77: =C77/C76-1 -> 0.026846312 | F77: =D77/D76-1 -> 0.1198228
B78: 03/16/2025 | C78: 23350.4 | D78: 1566.7 | E78: =C78/C77-1 -> -0.0071834468 | F78: =D78/D77-1 -> -0.016200942
B79: 45903 | C79: 22397.2 | D79: 1534.75 | E79: =C79/C78-1 -> -0.040821571 | F79: =D79/D78-1 -> -0.020393183
B80: 45691 | C80: 22552.5 | D80: 1557.95 | E80: =C80/C79-1 -> 0.0069339025 | F80: =D80/D79-1 -> 0.015116468
B81: 02/23/2025 | C81: 22124.7 | D81: 1575.05 | E81: =C81/C80-1 -> -0.018969072 | F81: =D81/D80-1 -> 0.010975962
B82: 02/16/2025 | C82: 22795.9 | D82: 1700.7 | E82: =C82/C81-1 -> 0.030337135 | F82: =D82/D81-1 -> 0.079775245
B83: 45902 | C83: 22929.25 | D83: 1711.25 | E83: =C83/C82-1 -> 0.0058497361 | F83: =D83/D82-1 -> 0.006203328
B84: 45690 | C84: 23559.95 | D84: 1725.65 | E84: =C84/C83-1 -> 0.027506351 | F84: =D84/D83-1 -> 0.0084149014
B85: 01/26/2025 | C85: 23508.4 | D85: 1725.45 | E85: =C85/C84-1 -> -0.0021880352 | F85: =D85/D84-1 -> -0.00011589836
B86: 01/19/2025 | C86: 23092.2 | D86: 1792.85 | E86: =C86/C85-1 -> -0.01770431 | F86: =D86/D85-1 -> 0.039062274
B87: 45992 | C87: 23203.2 | D87: 1788.9 | E87: =C87/C86-1 -> 0.0048068179 | F87: =D87/D86-1 -> -0.002203196
B88: 45778 | C88: 23431.5 | D88: 1988.42 | E88: =C88/C87-1 -> 0.0098391601 | F88: =D88/D87-1 -> 0.11153223
B89: 12/29/2024 | C89: 24004.75 | D89: 1940.13 | E89: =C89/C88-1 -> 0.02446493 | F89: =D89/D88-1 -> -0.024285614
B90: 12/22/2024 | C90: 23813.4 | D90: 1885.67 | E90: =C90/C89-1 -> -0.007971339 | F90: =D90/D89-1 -> -0.028070284
B91: 12/15/2024 | C91: 23587.5 | D91: 1904.95 | E91: =C91/C90-1 -> -0.0094862556 | F91: =D91/D90-1 -> 0.010224483
B92: 45516 | C92: 24768.3 | D92: 1962.21 | E92: =C92/C91-1 -> 0.050060413 | F92: =D92/D91-1 -> 0.030058532
B93: 45303 | C93: 24677.8 | D93: 1916.26 | E93: =C93/C92-1 -> -0.003653864 | F93: =D93/D92-1 -> -0.023417473
B94: 11/24/2024 | C94: 24131.1 | D94: 1841.86 | E94: =C94/C93-1 -> -0.022153514 | F94: =D94/D93-1 -> -0.038825629
B95: 11/17/2024 | C95: 23907.25 | D95: 1892.04 | E95: =C95/C94-1 -> -0.0092764109 | F95: =D95/D94-1 -> 0.027244199
B96: 45576 | C96: 23532.7 | D96: 1852.73 | E96: =C96/C95-1 -> -0.015666796 | F96: =D96/D95-1 -> -0.020776516
B97: 45362 | C97: 24148.2 | D97: 1831.35 | E97: =C97/C96-1 -> 0.026155095 | F97: =D97/D96-1 -> -0.011539728
B98: 10/27/2024 | C98: 24304.35 | D98: 1751.52 | E98: =C98/C97-1 -> 0.0064663205 | F98: =D98/D97-1 -> -0.043590794
B99: 10/20/2024 | C99: 24180.8 | D99: 1846.15 | E99: =C99/C98-1 -> -0.0050834521 | F99: =D99/D98-1 -> 0.054027359
B100: 10/13/2024 | C100: 24854.05 | D100: 1851.48 | E100: =C100/C99-1 -> 0.027842338 | F100: =D100/D99-1 -> 0.0028870893
B101: 45453 | C101: 24964.25 | D101: 1833.49 | E101: =C101/C100-1 -> 0.004433885 | F101: =D101/D100-1 -> -0.0097165511
B102: 09/29/2024 | C102: 25014.6 | D102: 1770.65 | E102: =C102/C101-1 -> 0.0020168841 | F102: =D102/D101-1 -> -0.034273435
B103: 09/22/2024 | C103: 26178.95 | D103: 1802.34 | E103: =C103/C102-1 -> 0.046546817 | F103: =D103/D102-1 -> 0.017897382
B104: 09/15/2024 | C104: 25790.95 | D104: 1754.16 | E104: =C104/C103-1 -> -0.014821068 | F104: =D104/D103-1 -> -0.026731915
B105: 45513 | C105: 25356.5 | D105: 1806.73 | E105: =C105/C104-1 -> -0.016845056 | F105: =D105/D104-1 -> 0.02996876
...
